<?xml version="1.0" encoding="UTF-8" standalone="no"?>
<BATCH xmlns="urn:mclsoftware.co.uk:hunterII" xmlns:xsd="http://www.w3.org/2001/XMLSchema" xmlns:xsi="http://www.w3.org/2001/XMLSchema-instance">
  <HEADER>
    <COUNT>19</COUNT>
    <ORIGINATOR>SHDFC</ORIGINATOR>
  </HEADER>
  <SUBMISSIONS>
    <SUBMISSION>
      <APP_VAL>1097519</APP_VAL>
      <TERM>120</TERM>
      <CLASSIFICATION>UNKNOWN</CLASSIFICATION>
      <IDENTIFIER>N_APPL05280459_NHOU</IDENTIFIER>
      <PRODUCT>NHL_IND</PRODUCT>
      <DATE>2023-09-13</DATE>
      <APP_DTE>2023-09-13</APP_DTE>
      <BRNCH_RGN>Delhi</BRNCH_RGN>
      <MA>
        <PAN>NYSPS2848B</PAN>
        <FST_NME>BALJEET</FST_NME>
        <LST_NME>SINGH</LST_NME>
        <DOB>1973-08-09</DOB>
        <AGE>50</AGE>
        <GNDR>MALE</GNDR>
        <MA_CA>
          <ADD>S O TEJ SINGH,SHAHPUR,SHAHPUR NANGAL TEJU</ADD>
          <CTY>Mahendragarh</CTY>
          <STE>Haryana</STE>
          <CTRY>India</CTRY>
          <PIN>123501</PIN>
        </MA_CA>
        <MA_PMA>
          <ADD>S O TEJ SINGH,SHAHPUR,SHAHPUR NANGAL TEJU</ADD>
          <CTY>Mahendragarh</CTY>
          <STE>Haryana</STE>
          <CTRY>India</CTRY>
          <PIN>123501</PIN>
        </MA_PMA>
        <MA_MT>
          <TEL_NO>8813937053</TEL_NO>
        </MA_MT>
        <MA_EMP>
          <ORG_NME>CHHILLAR Tent House</ORG_NME>
          <EMP_IND>OTHER</EMP_IND>
          <MA_EMP_AD>
            <ADD>NAGAL TEJU, BUS STANDBAWAL</ADD>
            <CTY>Mahendragarh</CTY>
            <STE>Haryana</STE>
            <CTRY>India</CTRY>
            <PIN>123501</PIN>
          </MA_EMP_AD>
          <MA_EMP_BT>
            <TEL_NO>8813937053</TEL_NO>
          </MA_EMP_BT>
        </MA_EMP>
      </MA>
      <JA>
        <PAN>BWKPC1323D</PAN>
        <FST_NME>SAHIL</FST_NME>
        <LST_NME>CHHILLAR</LST_NME>
        <DOB>2000-01-09</DOB>
        <AGE>23</AGE>
        <GNDR>MALE</GNDR>
        <JA_CA>
          <ADD>S0 BAJEET SINGH 33 NANGAL TEJPU,REWAN</ADD>
          <CTY>Mahendragarh</CTY>
          <STE>Haryana</STE>
          <CTRY>India</CTRY>
          <PIN>123501</PIN>
        </JA_CA>
      </JA>
      <RF>
        <FST_NME>BHUPENDER</FST_NME>
        <RF_MT>
          <TEL_NO>9416904527</TEL_NO>
        </RF_MT>
      </RF>
      <RF>
        <FST_NME>RAHUL</FST_NME>
        <RF_MT>
          <TEL_NO>9416904527</TEL_NO>
        </RF_MT>
      </RF>
    </SUBMISSION>
    <SUBMISSION>
      <APP_VAL>2990092</APP_VAL>
      <TERM>240</TERM>
      <CLASSIFICATION>UNKNOWN</CLASSIFICATION>
      <IDENTIFIER>N_APPL05285635_HOU</IDENTIFIER>
      <PRODUCT>HL_IND</PRODUCT>
      <DATE>2023-09-13</DATE>
      <APP_DTE>2023-09-13</APP_DTE>
      <BRNCH_RGN>Delhi</BRNCH_RGN>
      <MA>
        <PAN>CFQPR0904F</PAN>
        <FST_NME>DEEPAK</FST_NME>
        <LST_NME>RUKHAD</LST_NME>
        <DOB>1994-03-08</DOB>
        <AGE>29</AGE>
        <GNDR>MALE</GNDR>
        <MA_CA>
          <ADD>S O RAM KUMAR RUKHAD,696,TYPE 1 ADMIN FLATSGULABI BAGH,NORTH MALKA GANJ</ADD>
          <CTY>North Delhi</CTY>
          <STE>Delhi</STE>
          <CTRY>India</CTRY>
          <PIN>110007</PIN>
        </MA_CA>
        <MA_PMA>
          <ADD>S O RAM KUMAR RUKHAD,696,TYPE 1 ADMIN FLATSGULABI BAGH,NORTH MALKA GANJ</ADD>
          <CTY>North Delhi</CTY>
          <STE>Delhi</STE>
          <CTRY>India</CTRY>
          <PIN>110007</PIN>
        </MA_PMA>
        <MA_MT>
          <TEL_NO>8130782949</TEL_NO>
        </MA_MT>
        <MA_BNK>
          <BNK_NM>HDFC BANK</BNK_NM>
          <ACC_NO>3551</ACC_NO>
        </MA_BNK>
        <MA_EMP>
          <ORG_NME>AMERICAN EXPRESS INDIA PVT LTD</ORG_NME>
          <EMP_IND>SALES</EMP_IND>
          <MA_EMP_AD>
            <ADD>AMERICAN EXPRESS INDIA CAMPUSONE HORIZON CENTRE, AMERICAN EXPRESS, HARIZAN COLONY, DLF PHASE -5, SEC-43,GURUGRAM, HARYANA </ADD>
            <CTY>Gurgaon</CTY>
            <STE>Haryana</STE>
            <CTRY>India</CTRY>
            <PIN>122003</PIN>
          </MA_EMP_AD>
          <MA_EMP_BT>
            <TEL_NO>8130782949</TEL_NO>
          </MA_EMP_BT>
        </MA_EMP>
      </MA>
      <JA>
        <PAN>RHGPS5443M</PAN>
        <FST_NME>SEEMA</FST_NME>
        <LST_NME>SEEMA</LST_NME>
        <DOB>1972-01-01</DOB>
        <AGE>51</AGE>
        <GNDR>FEMALE</GNDR>
        <JA_CA>
          <ADD>C O RAM KUMAR RUKHAD,696,TYPE 1GULABI BAGH,GULABI BAGH,MALKA GANJNORTH</ADD>
          <CTY>North Delhi</CTY>
          <STE>Delhi</STE>
          <CTRY>India</CTRY>
          <PIN>110007</PIN>
        </JA_CA>
      </JA>
      <RF>
        <FST_NME>SURJEET</FST_NME>
        <RF_MT>
          <TEL_NO>7042888102</TEL_NO>
        </RF_MT>
      </RF>
      <RF>
        <FST_NME>SHOYETA</FST_NME>
        <RF_MT>
          <TEL_NO>7042888102</TEL_NO>
        </RF_MT>
      </RF>
    </SUBMISSION>
    <SUBMISSION>
      <APP_VAL>1515231</APP_VAL>
      <TERM>240</TERM>
      <CLASSIFICATION>UNKNOWN</CLASSIFICATION>
      <IDENTIFIER>W_APPL05282708_HOU</IDENTIFIER>
      <PRODUCT>HL_IND</PRODUCT>
      <DATE>2023-09-13</DATE>
      <APP_DTE>2023-09-13</APP_DTE>
      <BRNCH_RGN>Gujarat</BRNCH_RGN>
      <MA>
        <PAN>EYCPP6871C</PAN>
        <FST_NME>PATEL</FST_NME>
        <LST_NME>KETUL</LST_NME>
        <DOB>1996-09-06</DOB>
        <AGE>26</AGE>
        <GNDR>MALE</GNDR>
        <MA_CA>
          <ADD>MANOJBHAI CHANDUBHAI NR MAHADEVSTEMPLE BHUVALDI GAM SINGRWA   AHMEDABAD </ADD>
          <CTY>Ahmedabad</CTY>
          <STE>Gujarat</STE>
          <CTRY>India</CTRY>
          <PIN>382330</PIN>
        </MA_CA>
        <MA_PMA>
          <ADD>MANOJBHAI CHANDUBHAI NR MAHADEVSTEMPLE BHUVALDI GAM SINGRWA   AHMEDABAD </ADD>
          <CTY>Ahmedabad</CTY>
          <STE>Gujarat</STE>
          <CTRY>India</CTRY>
          <PIN>382330</PIN>
        </MA_PMA>
        <MA_MT>
          <TEL_NO>8128751690</TEL_NO>
        </MA_MT>
        <MA_BNK>
          <BNK_NM>AXIS BANK</BNK_NM>
          <ACC_NO>919010005290945</ACC_NO>
        </MA_BNK>
        <MA_EMP>
          <ORG_NME>FREEDOM MOBILE SHOP</ORG_NME>
          <EMP_IND>OTHER</EMP_IND>
          <MA_EMP_AD>
            <ADD>SHOP NO.24,SHYAM KUTIR NR 108 EMTICENTER HANSPURA NARODA AHMEDABAD </ADD>
            <CTY>Ahmedabad</CTY>
            <STE>Gujarat</STE>
            <CTRY>India</CTRY>
            <PIN>382330</PIN>
          </MA_EMP_AD>
          <MA_EMP_BT>
            <TEL_NO>8128751690</TEL_NO>
          </MA_EMP_BT>
        </MA_EMP>
      </MA>
      <JA>
        <PAN>BWYPP1297D</PAN>
        <FST_NME>PATEL</FST_NME>
        <LST_NME>DIPIKABEN</LST_NME>
        <DOB>1974-10-23</DOB>
        <AGE>48</AGE>
        <GNDR>FEMALE</GNDR>
        <JA_CA>
          <ADD>MANOJBHAI CHANDUBHAI NR MAHADEVSTEMPLE BHUVALDI GAM SINGRWA   AHMEDABAD </ADD>
          <CTY>Ahmedabad</CTY>
          <STE>Gujarat</STE>
          <CTRY>India</CTRY>
          <PIN>382330</PIN>
        </JA_CA>
      </JA>
      <JA>
        <PAN>AOYPP2761F</PAN>
        <FST_NME>MANOJKUMAR</FST_NME>
        <LST_NME>PATEL</LST_NME>
        <DOB>1967-06-01</DOB>
        <AGE>56</AGE>
        <GNDR>MALE</GNDR>
        <JA_CA>
          <ADD>NR MAHADEVS TEMPLEBHUVALDI GAMSINGRAVA</ADD>
          <CTY>Ahmedabad</CTY>
          <STE>Gujarat</STE>
          <CTRY>India</CTRY>
          <PIN>382330</PIN>
        </JA_CA>
      </JA>
      <BR>
        <ORG_CD>5920</ORG_CD>
        <ORG_NME>Andromeda Sales And Distribution PVT LTD</ORG_NME>
        <BR_ADD>
          <ADD>Ground Floor, H no.1-19-4, Sriram Nagar, East Godavari District, East Godavari, Andhra Pradesh </ADD>
          <CTY>Navi Mumbai</CTY>
          <STE>Maharashtra</STE>
          <PIN>401202</PIN>
          <CTRY>INDIA</CTRY>
        </BR_ADD>
      </BR>
      <RF>
        <FST_NME>RAJNIKANT</FST_NME>
        <LST_NME>MAKWANA</LST_NME>
        <RF_MT>
          <TEL_NO>7016946147</TEL_NO>
        </RF_MT>
      </RF>
      <RF>
        <FST_NME>JIGAR</FST_NME>
        <LST_NME>PATEL</LST_NME>
        <RF_MT>
          <TEL_NO>7016946147</TEL_NO>
        </RF_MT>
      </RF>
    </SUBMISSION>
    <SUBMISSION>
      <APP_VAL>3793348</APP_VAL>
      <TERM>216</TERM>
      <CLASSIFICATION>UNKNOWN</CLASSIFICATION>
      <IDENTIFIER>W_APPL05277619_HOU</IDENTIFIER>
      <PRODUCT>HL_IND</PRODUCT>
      <DATE>2023-09-13</DATE>
      <APP_DTE>2023-09-13</APP_DTE>
      <BRNCH_RGN>Gujarat</BRNCH_RGN>
      <MA>
        <PAN>ARXPR2796J</PAN>
        <FST_NME>RAI</FST_NME>
        <LST_NME>PAVANKUMAR</LST_NME>
        <DOB>1981-02-04</DOB>
        <AGE>42</AGE>
        <GNDR>MALE</GNDR>
        <MA_CA>
          <ADD>HOUSE NO.2,DIVYPRBHA SOCIETY MAHAVIRNAGAR NI SAME VIRATNAGARAHMEDABAD </ADD>
          <CTY>Ahmedabad</CTY>
          <STE>Gujarat</STE>
          <CTRY>India</CTRY>
          <PIN>382415</PIN>
        </MA_CA>
        <MA_PMA>
          <ADD>HOUSE NO.2,DIVYPRBHA SOCIETY MAHAVIRNAGAR NI SAME VIRATNAGARAHMEDABAD </ADD>
          <CTY>Ahmedabad</CTY>
          <STE>Gujarat</STE>
          <CTRY>India</CTRY>
          <PIN>382415</PIN>
        </MA_PMA>
        <MA_MT>
          <TEL_NO>9376521283</TEL_NO>
        </MA_MT>
        <MA_BNK>
          <BNK_NM>IDBI </BNK_NM>
          <ACC_NO>1280102000024578</ACC_NO>
        </MA_BNK>
        <MA_EMP>
          <ORG_NME>Aarohi Finishing situated </ORG_NME>
          <EMP_IND>OTHER</EMP_IND>
          <MA_EMP_AD>
            <ADD>75-1,AAROHI FINISHING,NARAYAN CO.OP.IND ESTATE OPP.SHRIRAM ROAD ODHAVAHMEDABAD</ADD>
            <CTY>Ahmedabad</CTY>
            <STE>Gujarat</STE>
            <CTRY>India</CTRY>
            <PIN>382415</PIN>
          </MA_EMP_AD>
          <MA_EMP_BT>
            <TEL_NO>9376521283</TEL_NO>
          </MA_EMP_BT>
        </MA_EMP>
      </MA>
      <JA>
        <PAN>EQQPR3047L</PAN>
        <FST_NME>RAI</FST_NME>
        <LST_NME>ANANDKUMAR</LST_NME>
        <DOB>1972-05-08</DOB>
        <AGE>51</AGE>
        <GNDR>MALE</GNDR>
        <JA_CA>
          <ADD>HOUSE NO.2,DIVYPRBHA SOCIETY MAHAVIRNAGAR NI SAME VIRATNAGARAHMEDABAD </ADD>
          <CTY>Ahmedabad</CTY>
          <STE>Gujarat</STE>
          <CTRY>India</CTRY>
          <PIN>382415</PIN>
        </JA_CA>
      </JA>
      <BR>
        <ORG_CD>5723</ORG_CD>
        <ORG_NME>FINANCIAL Zone</ORG_NME>
      </BR>
      <RF>
        <FST_NME>MANOJ</FST_NME>
        <LST_NME>BHAI</LST_NME>
        <RF_MT>
          <TEL_NO>9974431559</TEL_NO>
        </RF_MT>
      </RF>
      <RF>
        <FST_NME>BHARGAV</FST_NME>
        <LST_NME>BHAI</LST_NME>
        <RF_MT>
          <TEL_NO>9974431559</TEL_NO>
        </RF_MT>
      </RF>
    </SUBMISSION>
    <SUBMISSION>
      <APP_VAL>629562</APP_VAL>
      <TERM>180</TERM>
      <CLASSIFICATION>UNKNOWN</CLASSIFICATION>
      <IDENTIFIER>N_APPL05286031_NHOU</IDENTIFIER>
      <PRODUCT>NHL_IND</PRODUCT>
      <DATE>2023-09-13</DATE>
      <APP_DTE>2023-09-13</APP_DTE>
      <BRNCH_RGN>UP - Lucknow</BRNCH_RGN>
      <MA>
        <PAN>CDZPG2085H</PAN>
        <FST_NME>SUDHA</FST_NME>
        <LST_NME>GUPTA</LST_NME>
        <DOB>1973-07-05</DOB>
        <AGE>50</AGE>
        <GNDR>FEMALE</GNDR>
        <MA_CA>
          <ADD>66 138A  KACHHIYANA MOHAL </ADD>
          <CTY>Kanpur Dehat</CTY>
          <STE>Uttar Pradesh</STE>
          <CTRY>India</CTRY>
          <PIN>208001</PIN>
        </MA_CA>
        <MA_PMA>
          <ADD>66 138A  KACHHIYANA MOHAL </ADD>
          <CTY>Kanpur Dehat</CTY>
          <STE>Uttar Pradesh</STE>
          <CTRY>India</CTRY>
          <PIN>208001</PIN>
        </MA_PMA>
        <MA_MT>
          <TEL_NO>7408392522</TEL_NO>
        </MA_MT>
        <MA_EMP>
          <ORG_NME>Gupta General Store</ORG_NME>
          <EMP_IND>FOOD</EMP_IND>
          <MA_EMP_AD>
            <ADD>61 172 SITARAM MOHAL</ADD>
            <CTY>Kanpur Dehat</CTY>
            <STE>Uttar Pradesh</STE>
            <CTRY>India</CTRY>
            <PIN>208001</PIN>
          </MA_EMP_AD>
          <MA_EMP_BT>
            <TEL_NO>7408392522</TEL_NO>
          </MA_EMP_BT>
        </MA_EMP>
      </MA>
      <JA>
        <PAN>CXWPG9157R</PAN>
        <FST_NME>ALOK</FST_NME>
        <LST_NME>GUPTA</LST_NME>
        <DOB>1993-10-19</DOB>
        <AGE>29</AGE>
        <GNDR>MALE</GNDR>
        <JA_CA>
          <ADD>S O LATE RAM PRAKASH GUPTA,66 138 A KACHHIYANA MOHAL NAGAR</ADD>
          <CTY>Kanpur Dehat</CTY>
          <STE>Uttar Pradesh</STE>
          <CTRY>India</CTRY>
          <PIN>208001</PIN>
        </JA_CA>
      </JA>
      <RF>
        <FST_NME>MONIKA</FST_NME>
        <LST_NME>GUPTA</LST_NME>
        <RF_MT>
          <TEL_NO>8299429713</TEL_NO>
        </RF_MT>
      </RF>
      <RF>
        <FST_NME>SHASHANK</FST_NME>
        <LST_NME>KUMAR</LST_NME>
        <RF_MT>
          <TEL_NO>8299429713</TEL_NO>
        </RF_MT>
      </RF>
    </SUBMISSION>
    <SUBMISSION>
      <APP_VAL>1035747</APP_VAL>
      <TERM>180</TERM>
      <CLASSIFICATION>UNKNOWN</CLASSIFICATION>
      <IDENTIFIER>W_APPL05284646_NHOU</IDENTIFIER>
      <PRODUCT>NHL_IND</PRODUCT>
      <DATE>2023-09-13</DATE>
      <APP_DTE>2023-09-13</APP_DTE>
      <BRNCH_RGN>MH - Marathwada</BRNCH_RGN>
      <MA>
        <PAN>BUGPB9393E</PAN>
        <FST_NME>DHIRAJ</FST_NME>
        <MID_NME>VIJAY</MID_NME>
        <LST_NME>BOROLE</LST_NME>
        <DOB>1994-06-15</DOB>
        <AGE>29</AGE>
        <GNDR>MALE</GNDR>
        <MA_CA>
          <ADD> PLOT NO 15 SHIRPUR KANHALA ROAD RMS COLONY</ADD>
          <CTY>Jalgaon</CTY>
          <STE>Maharashtra</STE>
          <CTRY>India</CTRY>
          <PIN>425201</PIN>
        </MA_CA>
        <MA_PMA>
          <ADD> PLOT NO 15 SHIRPUR KANHALA ROAD RMS COLONY</ADD>
          <CTY>Jalgaon</CTY>
          <STE>Maharashtra</STE>
          <CTRY>India</CTRY>
          <PIN>425201</PIN>
        </MA_PMA>
        <MA_MT>
          <TEL_NO>7666266963</TEL_NO>
        </MA_MT>
        <MA_BNK>
          <BNK_NM>CENTRAL BANK OF INDIA</BNK_NM>
          <ACC_NO>5140565577</ACC_NO>
        </MA_BNK>
        <MA_EMP>
          <ORG_NME>M/s Shri Swami Samarth General store and provision</ORG_NME>
          <EMP_IND>OTHER</EMP_IND>
          <MA_EMP_AD>
            <ADD>PLOT NO 15 SHIRPUR KANHALA ROAD BHUSAWAL </ADD>
            <CTY>Jalgaon</CTY>
            <STE>Maharashtra</STE>
            <CTRY>India</CTRY>
            <PIN>425201</PIN>
          </MA_EMP_AD>
          <MA_EMP_BT>
            <TEL_NO>7666266963</TEL_NO>
          </MA_EMP_BT>
        </MA_EMP>
      </MA>
      <RF>
        <FST_NME>DHIRAJ</FST_NME>
        <LST_NME>CHAUDHARI</LST_NME>
        <RF_MT>
          <TEL_NO>9730447664</TEL_NO>
        </RF_MT>
      </RF>
      <RF>
        <FST_NME>VAIBHAV</FST_NME>
        <LST_NME>BOROLE</LST_NME>
        <RF_MT>
          <TEL_NO>9730447664</TEL_NO>
        </RF_MT>
      </RF>
    </SUBMISSION>
    <SUBMISSION>
      <APP_VAL>1059387</APP_VAL>
      <TERM>120</TERM>
      <CLASSIFICATION>UNKNOWN</CLASSIFICATION>
      <IDENTIFIER>N_APPL05285262_NHOU</IDENTIFIER>
      <PRODUCT>NHL_IND</PRODUCT>
      <DATE>2023-09-13</DATE>
      <APP_DTE>2023-09-13</APP_DTE>
      <BRNCH_RGN>UP - Lucknow</BRNCH_RGN>
      <MA>
        <PAN>BVFPG2910J</PAN>
        <FST_NME>RAJ</FST_NME>
        <MID_NME>KISHOR</MID_NME>
        <LST_NME>GUPTA</LST_NME>
        <DOB>1998-03-19</DOB>
        <AGE>25</AGE>
        <GNDR>MALE</GNDR>
        <MA_CA>
          <ADD>S O KASHI NATH GUPTA MADHOPUR,KURAHUAN,KURAHUWAN</ADD>
          <CTY>Varanasi</CTY>
          <STE>Uttar Pradesh</STE>
          <CTRY>India</CTRY>
          <PIN>221011</PIN>
        </MA_CA>
        <MA_PMA>
          <ADD>S O KASHI NATH GUPTA MADHOPUR,KURAHUAN,KURAHUWAN</ADD>
          <CTY>Varanasi</CTY>
          <STE>Uttar Pradesh</STE>
          <CTRY>India</CTRY>
          <PIN>221011</PIN>
        </MA_PMA>
        <MA_MT>
          <TEL_NO>9569203556</TEL_NO>
        </MA_MT>
        <MA_EMP>
          <ORG_NME>RAJ COLLECTION CENTER  </ORG_NME>
          <EMP_IND>OTHER</EMP_IND>
          <MA_EMP_AD>
            <ADD>AMRA BYPASS CHITAIPURUPASNA NAGAR</ADD>
            <CTY>Varanasi</CTY>
            <STE>Uttar Pradesh</STE>
            <CTRY>India</CTRY>
            <PIN>221011</PIN>
          </MA_EMP_AD>
          <MA_EMP_BT>
            <TEL_NO>9569203556</TEL_NO>
          </MA_EMP_BT>
        </MA_EMP>
      </MA>
      <JA>
        <PAN>BJPPG1042P</PAN>
        <FST_NME>KASHI</FST_NME>
        <MID_NME>NATH</MID_NME>
        <LST_NME>GUPTA</LST_NME>
        <DOB>1959-01-01</DOB>
        <AGE>64</AGE>
        <GNDR>MALE</GNDR>
        <JA_CA>
          <ADD>S O GHUR SAW,MADHOPUR,KURAHUWAN</ADD>
          <CTY>Varanasi</CTY>
          <STE>Uttar Pradesh</STE>
          <CTRY>India</CTRY>
          <PIN>221011</PIN>
        </JA_CA>
      </JA>
      <JA>
        <PAN>CJBPD6348A</PAN>
        <FST_NME>PARVATI</FST_NME>
        <LST_NME>DEVI</LST_NME>
        <DOB>1974-07-15</DOB>
        <AGE>49</AGE>
        <GNDR>FEMALE</GNDR>
        <JA_CA>
          <ADD>S O GHUR SAW,MADHOPUR,KURAHUWAN</ADD>
          <CTY>Varanasi</CTY>
          <STE>Uttar Pradesh</STE>
          <CTRY>India</CTRY>
          <PIN>221011</PIN>
        </JA_CA>
      </JA>
      <RF>
        <FST_NME>KISHAN</FST_NME>
        <LST_NME>KISHOR</LST_NME>
        <RF_MT>
          <TEL_NO>9198858624</TEL_NO>
        </RF_MT>
      </RF>
      <RF>
        <FST_NME>GAURAV</FST_NME>
        <LST_NME>MAURYA</LST_NME>
        <RF_MT>
          <TEL_NO>9198858624</TEL_NO>
        </RF_MT>
      </RF>
    </SUBMISSION>
    <SUBMISSION>
      <APP_VAL>520389</APP_VAL>
      <TERM>180</TERM>
      <CLASSIFICATION>UNKNOWN</CLASSIFICATION>
      <IDENTIFIER>N_APPL05286245_NHOU</IDENTIFIER>
      <PRODUCT>NHL_IND</PRODUCT>
      <DATE>2023-09-13</DATE>
      <APP_DTE>2023-09-13</APP_DTE>
      <BRNCH_RGN>UP - Meerut</BRNCH_RGN>
      <MA>
        <PAN>HHAPS6589G</PAN>
        <FST_NME>SALMAN</FST_NME>
        <LST_NME>SALMAN</LST_NME>
        <DOB>1994-01-01</DOB>
        <AGE>29</AGE>
        <GNDR>MALE</GNDR>
        <MA_CA>
          <ADD>S O MOHD IKBAL,145 K,TELIVALA</ADD>
          <CTY>Haridwar</CTY>
          <STE>Uttarakhand</STE>
          <CTRY>India</CTRY>
          <PIN>247666</PIN>
        </MA_CA>
        <MA_PMA>
          <ADD>S O MOHD IKBAL,145 K,TELIVALA</ADD>
          <CTY>Haridwar</CTY>
          <STE>Uttarakhand</STE>
          <CTRY>India</CTRY>
          <PIN>247666</PIN>
        </MA_PMA>
        <MA_MT>
          <TEL_NO>9536094136</TEL_NO>
        </MA_MT>
        <MA_EMP>
          <ORG_NME>Civil contractor</ORG_NME>
          <EMP_IND>OTHER</EMP_IND>
          <MA_EMP_AD>
            <ADD>RAMNAGARPADLIROORKEE </ADD>
            <CTY>Roorkee</CTY>
            <STE>Uttarakhand</STE>
            <CTRY>India</CTRY>
            <PIN>247667</PIN>
          </MA_EMP_AD>
          <MA_EMP_BT>
            <TEL_NO>9536094136</TEL_NO>
          </MA_EMP_BT>
        </MA_EMP>
      </MA>
      <JA>
        <PAN>ENPPA4911L</PAN>
        <FST_NME>ASMIN</FST_NME>
        <LST_NME>ASMIN</LST_NME>
        <DOB>1998-05-01</DOB>
        <AGE>25</AGE>
        <GNDR>FEMALE</GNDR>
        <JA_CA>
          <ADD>C O SALMAN,TELLIWALA,PADLI GUJJARPOST MILAP NAGAR,PADLI GUZZAR</ADD>
          <CTY>Roorkee</CTY>
          <STE>Uttarakhand</STE>
          <CTRY>India</CTRY>
          <PIN>247667</PIN>
        </JA_CA>
      </JA>
      <RF>
        <FST_NME>ATIK</FST_NME>
        <LST_NME>REHMAAN</LST_NME>
        <RF_MT>
          <TEL_NO>8126888768</TEL_NO>
        </RF_MT>
      </RF>
      <RF>
        <FST_NME>MURSALEEN</FST_NME>
        <RF_MT>
          <TEL_NO>8126888768</TEL_NO>
        </RF_MT>
      </RF>
    </SUBMISSION>
    <SUBMISSION>
      <APP_VAL>825116</APP_VAL>
      <TERM>180</TERM>
      <CLASSIFICATION>UNKNOWN</CLASSIFICATION>
      <IDENTIFIER>C_APPL05284629_NHOU</IDENTIFIER>
      <PRODUCT>NHL_IND</PRODUCT>
      <DATE>2023-09-13</DATE>
      <APP_DTE>2023-09-13</APP_DTE>
      <BRNCH_RGN>MP</BRNCH_RGN>
      <MA>
        <PAN>BSEPC0729F</PAN>
        <FST_NME>IMRAN</FST_NME>
        <LST_NME>CHOUHAN</LST_NME>
        <DOB>1996-12-20</DOB>
        <AGE>26</AGE>
        <GNDR>MALE</GNDR>
        <MA_CA>
          <ADD>C O MOHD RAFIQUE,OPPOSITE MAHAK VATIKA,6SUNDAR BAG COLONY</ADD>
          <CTY>Indore</CTY>
          <STE>Madhya Pradesh</STE>
          <CTRY>India</CTRY>
          <PIN>452010</PIN>
        </MA_CA>
        <MA_PMA>
          <ADD>C O MOHD RAFIQUE,OPPOSITE MAHAK VATIKA,6SUNDAR BAG COLONY</ADD>
          <CTY>Indore</CTY>
          <STE>Madhya Pradesh</STE>
          <CTRY>India</CTRY>
          <PIN>452010</PIN>
        </MA_PMA>
        <MA_PROP>
          <ADD>indoreinodreInodore</ADD>
          <CTY>Indore</CTY>
          <STE>Madhya Pradesh</STE>
          <CTRY>India</CTRY>
          <PIN>452001</PIN>
        </MA_PROP>
        <MA_MT>
          <TEL_NO>9827044191</TEL_NO>
        </MA_MT>
        <MA_EMP>
          <ORG_NME>IMRAN EGG CENTER</ORG_NME>
          <EMP_IND>FOOD</EMP_IND>
          <MA_EMP_AD>
            <ADD>4 SUNDER BAG COLONY </ADD>
            <CTY>Indore</CTY>
            <STE>Madhya Pradesh</STE>
            <CTRY>India</CTRY>
            <PIN>452001</PIN>
          </MA_EMP_AD>
          <MA_EMP_BT>
            <TEL_NO>9827044191</TEL_NO>
          </MA_EMP_BT>
        </MA_EMP>
      </MA>
      <JA>
        <PAN>CQLPC6080M</PAN>
        <FST_NME>MUMTAJ</FST_NME>
        <LST_NME>CHOUHAN</LST_NME>
        <DOB>1994-06-24</DOB>
        <AGE>29</AGE>
        <GNDR>FEMALE</GNDR>
        <JA_CA>
          <ADD>W O MO IMRAN CHOUHAN,09,SUNDAR BAAG COLONYMR 9 ROAD,KHAJRANA</ADD>
          <CTY>Indore</CTY>
          <STE>Madhya Pradesh</STE>
          <CTRY>India</CTRY>
          <PIN>452010</PIN>
        </JA_CA>
      </JA>
      <RF>
        <FST_NME>MOHSIN</FST_NME>
        <LST_NME>CHOUHAN</LST_NME>
        <RF_MT>
          <TEL_NO>9827711114</TEL_NO>
        </RF_MT>
      </RF>
      <RF>
        <FST_NME>SHAHRUKH</FST_NME>
        <RF_MT>
          <TEL_NO>9827711114</TEL_NO>
        </RF_MT>
      </RF>
    </SUBMISSION>
    <SUBMISSION>
      <APP_VAL>609708</APP_VAL>
      <TERM>144</TERM>
      <CLASSIFICATION>UNKNOWN</CLASSIFICATION>
      <IDENTIFIER>W_APPL05286221_NHOU</IDENTIFIER>
      <PRODUCT>NHL_IND</PRODUCT>
      <DATE>2023-09-13</DATE>
      <APP_DTE>2023-09-13</APP_DTE>
      <BRNCH_RGN>MH - Pune</BRNCH_RGN>
      <MA>
        <PAN>BXOPB6487N</PAN>
        <FST_NME>ANIL</FST_NME>
        <MID_NME>SARJERAO</MID_NME>
        <LST_NME>BARGE</LST_NME>
        <DOB>1966-01-18</DOB>
        <AGE>57</AGE>
        <GNDR>MALE</GNDR>
        <MA_CA>
          <ADD>S O SARJERAO BARGE,DEGAON ROAD BOARVEL JAVAL,AT PO-CHINCHANER VANDANSATARA MAHARASHTRA</ADD>
          <CTY>Satara</CTY>
          <STE>Maharashtra</STE>
          <CTRY>India</CTRY>
          <PIN>415004</PIN>
        </MA_CA>
        <MA_PMA>
          <ADD>S O SARJERAO BARGE,DEGAON ROAD BOARVEL JAVAL,AT PO-CHINCHANER VANDANSATARA MAHARASHTRA</ADD>
          <CTY>Satara</CTY>
          <STE>Maharashtra</STE>
          <CTRY>India</CTRY>
          <PIN>415004</PIN>
        </MA_PMA>
        <MA_MT>
          <TEL_NO>9763279947</TEL_NO>
        </MA_MT>
        <MA_BNK>
          <BNK_NM>STATE BANK OF INDIA</BNK_NM>
          <ACC_NO>37791505484</ACC_NO>
        </MA_BNK>
        <MA_EMP>
          <ORG_NME>SHREE JANAI TRADERS</ORG_NME>
          <EMP_IND>OTHER</EMP_IND>
          <MA_EMP_AD>
            <ADD>AT CHINCHNER VANDAN SATARA RAHIMATPUR ROAD SATARA</ADD>
            <CTY>Satara</CTY>
            <STE>Maharashtra</STE>
            <CTRY>India</CTRY>
            <PIN>415004</PIN>
          </MA_EMP_AD>
          <MA_EMP_BT>
            <TEL_NO>9763279947</TEL_NO>
          </MA_EMP_BT>
        </MA_EMP>
      </MA>
      <JA>
        <PAN>CGPPG1596Q</PAN>
        <FST_NME>AARADHANA</FST_NME>
        <MID_NME>PRAVIN</MID_NME>
        <LST_NME>GHORPADE</LST_NME>
        <DOB>1997-07-29</DOB>
        <AGE>26</AGE>
        <GNDR>FEMALE</GNDR>
        <JA_CA>
          <ADD>AT POST GOJEGAON TALUKA SATARA GOJEGAON SATARA GIJEGAONMAHARASHTRA</ADD>
          <CTY>Satara</CTY>
          <STE>Maharashtra</STE>
          <CTRY>India</CTRY>
          <PIN>415004</PIN>
        </JA_CA>
      </JA>
      <RF>
        <FST_NME>AJIT</FST_NME>
        <LST_NME>BARGE</LST_NME>
        <RF_MT>
          <TEL_NO>7028273956</TEL_NO>
        </RF_MT>
      </RF>
      <RF>
        <FST_NME>NAVNATH</FST_NME>
        <LST_NME>BARGE</LST_NME>
        <RF_MT>
          <TEL_NO>7028273956</TEL_NO>
        </RF_MT>
      </RF>
    </SUBMISSION>
    <SUBMISSION>
      <APP_VAL>350863</APP_VAL>
      <TERM>240</TERM>
      <CLASSIFICATION>UNKNOWN</CLASSIFICATION>
      <IDENTIFIER>N_APPL05282022_NHOU</IDENTIFIER>
      <PRODUCT>NHL_IND</PRODUCT>
      <DATE>2023-09-13</DATE>
      <APP_DTE>2023-09-13</APP_DTE>
      <BRNCH_RGN>Burari</BRNCH_RGN>
      <MA>
        <PAN>BWPPS7330R</PAN>
        <FST_NME>VISHAL</FST_NME>
        <LST_NME>SAMUEL</LST_NME>
        <DOB>1983-11-26</DOB>
        <AGE>39</AGE>
        <GNDR>MALE</GNDR>
        <MA_CA>
          <ADD>S O ROBERT BENJIMEN,2109 3 TURKMAN GATE,CHRUCH COMPOUNDAJMERI GATE,CENTRAL</ADD>
          <CTY>Central Delhi</CTY>
          <STE>Delhi</STE>
          <CTRY>India</CTRY>
          <PIN>110002</PIN>
        </MA_CA>
        <MA_PMA>
          <ADD>S O ROBERT BENJIMEN,2109 3 TURKMAN GATE,CHRUCH COMPOUNDAJMERI GATE,CENTRAL</ADD>
          <CTY>Central Delhi</CTY>
          <STE>Delhi</STE>
          <CTRY>India</CTRY>
          <PIN>110002</PIN>
        </MA_PMA>
        <MA_PROP>
          <ADD>2109 AND 3 AJMERI GATECENTRAL DELHI</ADD>
          <CTY>Central Delhi</CTY>
          <STE>Delhi</STE>
          <CTRY>India</CTRY>
          <PIN>110002</PIN>
        </MA_PROP>
        <MA_MT>
          <TEL_NO>9690097747</TEL_NO>
        </MA_MT>
        <MA_BNK>
          <BNK_NM>BANK OF MAHARASHTRA</BNK_NM>
          <ACC_NO>60297906154</ACC_NO>
        </MA_BNK>
        <MA_ID>
          <DOC_TYP>PAN CARD</DOC_TYP>
          <DOC_NO>BWPPS7330R</DOC_NO>
        </MA_ID>
        <MA_EMP>
          <ORG_NME>Travel Solutions</ORG_NME>
          <EMP_IND>TRAVEL</EMP_IND>
          <MA_EMP_AD>
            <ADD>2109 AND 3 AJMERI GATECENTRAL DELHI</ADD>
            <CTY>Central Delhi</CTY>
            <STE>Delhi</STE>
            <CTRY>India</CTRY>
            <PIN>110002</PIN>
          </MA_EMP_AD>
          <MA_EMP_BT>
            <TEL_NO>9690097747</TEL_NO>
          </MA_EMP_BT>
        </MA_EMP>
      </MA>
      <JA>
        <PAN>CHKPJ6877R</PAN>
        <FST_NME>JYOTI</FST_NME>
        <LST_NME>JYOTI</LST_NME>
        <DOB>1993-07-02</DOB>
        <AGE>30</AGE>
        <GNDR>FEMALE</GNDR>
        <JA_CA>
          <ADD>C O VISHAL SAMUEL,H NO 2109 3,TURKMAN GATECHURCH COMPOUND,DARYA GANJ,CENTRAL</ADD>
          <CTY>Central Delhi</CTY>
          <STE>Delhi</STE>
          <CTRY>India</CTRY>
          <PIN>110002</PIN>
        </JA_CA>
      </JA>
      <RF>
        <FST_NME>ANITA</FST_NME>
        <RF_MT>
          <TEL_NO>9625132471</TEL_NO>
        </RF_MT>
      </RF>
      <RF>
        <FST_NME>ABHISHEK</FST_NME>
        <RF_MT>
          <TEL_NO>9625132471</TEL_NO>
        </RF_MT>
      </RF>
    </SUBMISSION>
    <SUBMISSION>
      <APP_VAL>2984527</APP_VAL>
      <TERM>180</TERM>
      <CLASSIFICATION>UNKNOWN</CLASSIFICATION>
      <IDENTIFIER>N_APPL05279780_NHOU</IDENTIFIER>
      <PRODUCT>NHL_IND</PRODUCT>
      <DATE>2023-09-13</DATE>
      <APP_DTE>2023-09-13</APP_DTE>
      <BRNCH_RGN>Delhi-Dwarka More</BRNCH_RGN>
      <MA>
        <PAN>AOAPS8918P</PAN>
        <FST_NME>MANPREET</FST_NME>
        <MID_NME>SINGH</MID_NME>
        <LST_NME>SETHI</LST_NME>
        <DOB>1977-04-20</DOB>
        <AGE>46</AGE>
        <GNDR>MALE</GNDR>
        <MA_CA>
          <ADD>S O AMARJIT SINGH SETHI,14 FIRST FLOOR,CHURCH ROADBHOGAL,JANGPURA,SOUTH JUNGPURA</ADD>
          <CTY>South Delhi</CTY>
          <STE>Delhi</STE>
          <CTRY>India</CTRY>
          <PIN>110014</PIN>
        </MA_CA>
        <MA_PMA>
          <ADD>S O AMARJIT SINGH SETHI,14 FIRST FLOOR,CHURCH ROADBHOGAL,JANGPURA,SOUTH JUNGPURA</ADD>
          <CTY>South Delhi</CTY>
          <STE>Delhi</STE>
          <CTRY>India</CTRY>
          <PIN>110014</PIN>
        </MA_PMA>
        <MA_MT>
          <TEL_NO>9810224434</TEL_NO>
        </MA_MT>
        <MA_EMA>
          <EMA_ADD>CARDREAMS1@GMAIL.COM</EMA_ADD>
        </MA_EMA>
        <MA_BNK>
          <BNK_NM>UCO BANK</BNK_NM>
          <ACC_NO>02490110027400</ACC_NO>
        </MA_BNK>
        <MA_EMP>
          <ORG_NME>Car Dreams. </ORG_NME>
          <EMP_IND>OTHER</EMP_IND>
          <MA_EMP_AD>
            <ADD>34,1 DOUBLE STOREYASHOK NAGAR, TILAK NAGARNEW DELHI</ADD>
            <CTY>West Delhi</CTY>
            <STE>Delhi</STE>
            <CTRY>India</CTRY>
            <PIN>110018</PIN>
          </MA_EMP_AD>
          <MA_EMP_BT>
            <TEL_NO>9810224434</TEL_NO>
          </MA_EMP_BT>
        </MA_EMP>
      </MA>
      <JA>
        <PAN>AUZPS0563M</PAN>
        <FST_NME>SANDEEP</FST_NME>
        <MID_NME>SINGH</MID_NME>
        <LST_NME>SETHI</LST_NME>
        <DOB>1973-06-26</DOB>
        <AGE>50</AGE>
        <GNDR>MALE</GNDR>
        <JA_CA>
          <ADD>S O AMARJEET SINGH,14,CHURCH ROADBHOGAL,JANGPURA,SOUTH JUNGPURA</ADD>
          <CTY>South Delhi</CTY>
          <STE>Delhi</STE>
          <CTRY>India</CTRY>
          <PIN>110014</PIN>
        </JA_CA>
      </JA>
      <RF>
        <FST_NME>ARVINDER</FST_NME>
        <LST_NME>SINGH</LST_NME>
        <RF_MT>
          <TEL_NO>9999555955</TEL_NO>
        </RF_MT>
      </RF>
      <RF>
        <FST_NME>HARGUN</FST_NME>
        <LST_NME>CHADHA</LST_NME>
        <RF_MT>
          <TEL_NO>9999555955</TEL_NO>
        </RF_MT>
      </RF>
    </SUBMISSION>
    <SUBMISSION>
      <APP_VAL>1195064</APP_VAL>
      <TERM>180</TERM>
      <CLASSIFICATION>UNKNOWN</CLASSIFICATION>
      <IDENTIFIER>N_APPL05285125_NHOU</IDENTIFIER>
      <PRODUCT>NHL_IND</PRODUCT>
      <DATE>2023-09-13</DATE>
      <APP_DTE>2023-09-13</APP_DTE>
      <BRNCH_RGN>Delhi-Bhogal</BRNCH_RGN>
      <MA>
        <PAN>BTAPN5554L</PAN>
        <FST_NME>JITENDER</FST_NME>
        <LST_NME>NAGAR</LST_NME>
        <DOB>1997-06-14</DOB>
        <AGE>26</AGE>
        <GNDR>MALE</GNDR>
        <MA_CA>
          <ADD>S O ARVIND NAGAR,1019-B,NYAY KHAND-1INDIRAPURAM,SHIPRA SUN</ADD>
          <CTY>Ghaziabad</CTY>
          <STE>Uttar Pradesh</STE>
          <CTRY>India</CTRY>
          <PIN>201014</PIN>
        </MA_CA>
        <MA_PMA>
          <ADD>S O ARVIND NAGAR,1019-B,NYAY KHAND-1INDIRAPURAM,SHIPRA SUN</ADD>
          <CTY>Ghaziabad</CTY>
          <STE>Uttar Pradesh</STE>
          <CTRY>India</CTRY>
          <PIN>201014</PIN>
        </MA_PMA>
        <MA_MT>
          <TEL_NO>7836052768</TEL_NO>
        </MA_MT>
        <MA_BNK>
          <BNK_NM>SOUTH INDIAN BANK</BNK_NM>
          <ACC_NO>0556053000004164</ACC_NO>
        </MA_BNK>
        <MA_EMP>
          <ORG_NME>CLICK AND CAPTURE PHOTO STUDIO </ORG_NME>
          <EMP_IND>OTHER</EMP_IND>
          <MA_EMP_AD>
            <ADD>SHOP NO -9A 1ST FLOOR GAUR CITY -2GREATER NOIDA UTTAR PRADESH </ADD>
            <CTY>Ghaziabad</CTY>
            <STE>Uttar Pradesh</STE>
            <CTRY>India</CTRY>
            <PIN>201009</PIN>
          </MA_EMP_AD>
          <MA_EMP_BT>
            <TEL_NO>7836052768</TEL_NO>
          </MA_EMP_BT>
        </MA_EMP>
      </MA>
      <JA>
        <PAN>BJCPA7114F</PAN>
        <FST_NME>ARVIND</FST_NME>
        <LST_NME>ARVIND</LST_NME>
        <DOB>1976-08-02</DOB>
        <AGE>47</AGE>
        <GNDR>MALE</GNDR>
        <JA_CA>
          <ADD>C O GENDALAL,1019 B,NYAY KHAND 1INDIRAPURAM,SHIPRA SUN</ADD>
          <CTY>Ghaziabad</CTY>
          <STE>Uttar Pradesh</STE>
          <CTRY>India</CTRY>
          <PIN>201014</PIN>
        </JA_CA>
      </JA>
      <JA>
        <PAN>DZZPD2575Q</PAN>
        <FST_NME>SIMA</FST_NME>
        <LST_NME>DEVI</LST_NME>
        <DOB>1974-05-01</DOB>
        <AGE>49</AGE>
        <GNDR>FEMALE</GNDR>
        <JA_CA>
          <ADD>W O ARVIND KUMAR,1019-8,NYAY W KHAND-1 INDIRAPURAMSHIPRA 1 SUN</ADD>
          <CTY>Ghaziabad</CTY>
          <STE>Uttar Pradesh</STE>
          <CTRY>India</CTRY>
          <PIN>201014</PIN>
        </JA_CA>
      </JA>
      <RF>
        <FST_NME>RAJ</FST_NME>
        <LST_NME>KUMAR</LST_NME>
        <RF_MT>
          <TEL_NO>9350034731</TEL_NO>
        </RF_MT>
      </RF>
      <RF>
        <FST_NME>SALIM</FST_NME>
        <RF_MT>
          <TEL_NO>9350034731</TEL_NO>
        </RF_MT>
      </RF>
    </SUBMISSION>
    <SUBMISSION>
      <APP_VAL>733598</APP_VAL>
      <TERM>180</TERM>
      <CLASSIFICATION>UNKNOWN</CLASSIFICATION>
      <IDENTIFIER>N_APPL05286296_NHOU</IDENTIFIER>
      <PRODUCT>NHL_IND</PRODUCT>
      <DATE>2023-09-13</DATE>
      <APP_DTE>2023-09-13</APP_DTE>
      <BRNCH_RGN>Lucknow-Ayodhya Road</BRNCH_RGN>
      <MA>
        <PAN>FHIPK7127N</PAN>
        <FST_NME>NARESH</FST_NME>
        <LST_NME>KANAUJIYA</LST_NME>
        <DOB>1981-10-14</DOB>
        <AGE>41</AGE>
        <GNDR>MALE</GNDR>
        <MA_CA>
          <ADD>13-B NARYAN NAGAR FAIZABAD ROAD, Lucknow Indira Nagar S.O, Uttar Pradesh, India 226016</ADD>
          <CTY>Lucknow</CTY>
          <STE>Uttar Pradesh</STE>
          <CTRY>India</CTRY>
          <PIN>226016</PIN>
        </MA_CA>
        <MA_PMA>
          <ADD>112-A RAVINDRA PALLI FAIZABAD ROAD INDRA NAGAR S.O LUCKNOW UTTAR PRADESH 226016</ADD>
          <CTY>Lucknow</CTY>
          <STE>Uttar Pradesh</STE>
          <CTRY>India</CTRY>
          <PIN>226016</PIN>
        </MA_PMA>
        <MA_MT>
          <TEL_NO>8953667127</TEL_NO>
        </MA_MT>
        <MA_EMA>
          <EMA_ADD>NARESHKANAUJIYA2@GMAIL.COM</EMA_ADD>
        </MA_EMA>
      </MA>
      <JA>
        <PAN>JQCPK7742G</PAN>
        <FST_NME>MEERA</FST_NME>
        <LST_NME>KANAUJIYA</LST_NME>
        <DOB>1984-01-01</DOB>
        <AGE>39</AGE>
        <GNDR>FEMALE</GNDR>
        <JA_CA>
          <ADD>B-13 NARAYAN NAGAR FAIZABAD ROAD INDRA NAGAR LUCKNOW LUCKNOW 226016</ADD>
          <CTY>Lucknow</CTY>
          <STE>Uttar Pradesh</STE>
          <CTRY>India</CTRY>
          <PIN>226016</PIN>
        </JA_CA>
      </JA>
      <BR>
        <ORG_CD>5277</ORG_CD>
        <ORG_NME>Square Capital Advisory Pvt Ltd</ORG_NME>
      </BR>
      <RF>
        <FST_NME>MONA</FST_NME>
        <RF_MT>
          <TEL_NO>9140130983</TEL_NO>
        </RF_MT>
      </RF>
      <RF>
        <FST_NME>SUDHEER</FST_NME>
        <LST_NME>SRIVASTAVA</LST_NME>
        <RF_MT>
          <TEL_NO>9140130983</TEL_NO>
        </RF_MT>
      </RF>
    </SUBMISSION>
    <SUBMISSION>
      <APP_VAL>853322</APP_VAL>
      <TERM>156</TERM>
      <CLASSIFICATION>UNKNOWN</CLASSIFICATION>
      <IDENTIFIER>W_APPL05285410_HOU</IDENTIFIER>
      <PRODUCT>HL_IND</PRODUCT>
      <DATE>2023-09-13</DATE>
      <APP_DTE>2023-09-13</APP_DTE>
      <BRNCH_RGN>Nandurbar</BRNCH_RGN>
      <MA>
        <PAN>BPOPJ7471Q</PAN>
        <FST_NME>JYOTI</FST_NME>
        <MID_NME>VIJAYKUMAR</MID_NME>
        <LST_NME>JADHAV</LST_NME>
        <DOB>1982-05-08</DOB>
        <AGE>41</AGE>
        <GNDR>FEMALE</GNDR>
        <MA_CA>
          <ADD>PLOT NO 22 SUYOG COLONYSAKRI </ADD>
          <CTY>Dhule</CTY>
          <STE>Maharashtra</STE>
          <CTRY>India</CTRY>
          <PIN>424304</PIN>
        </MA_CA>
        <MA_PMA>
          <ADD>RUPAI NAGAR KASHIPUR RASTA SAKRISAKRI </ADD>
          <CTY>Dhule</CTY>
          <STE>Maharashtra</STE>
          <CTRY>India</CTRY>
          <PIN>424304</PIN>
        </MA_PMA>
        <MA_MT>
          <TEL_NO>7507833860</TEL_NO>
        </MA_MT>
        <MA_EMP>
          <ORG_NME>Swamini Beauty Parlor</ORG_NME>
          <EMP_IND>OTHER</EMP_IND>
          <MA_EMP_AD>
            <ADD>PLOT NO 22 SUYOG COLONY</ADD>
            <CTY>Dhule</CTY>
            <STE>Maharashtra</STE>
            <CTRY>India</CTRY>
            <PIN>424304</PIN>
          </MA_EMP_AD>
          <MA_EMP_BT>
            <TEL_NO>7507833860</TEL_NO>
          </MA_EMP_BT>
        </MA_EMP>
      </MA>
      <JA>
        <FST_NME>RAJANI</FST_NME>
        <MID_NME>DAULAT</MID_NME>
        <LST_NME>PATIL</LST_NME>
        <DOB>1956-06-01</DOB>
        <AGE>67</AGE>
        <GNDR>FEMALE</GNDR>
        <JA_CA>
          <ADD>PLOT NO 22 SUYOG COLONY</ADD>
          <CTY>Dhule</CTY>
          <STE>Maharashtra</STE>
          <CTRY>India</CTRY>
          <PIN>424304</PIN>
        </JA_CA>
      </JA>
      <RF>
        <FST_NME>PRANALI</FST_NME>
        <LST_NME>SONAWANE</LST_NME>
        <RF_MT>
          <TEL_NO>8080585367</TEL_NO>
        </RF_MT>
      </RF>
      <RF>
        <FST_NME>SANGITA</FST_NME>
        <LST_NME>HIRE</LST_NME>
        <RF_MT>
          <TEL_NO>8080585367</TEL_NO>
        </RF_MT>
      </RF>
    </SUBMISSION>
    <SUBMISSION>
      <APP_VAL>653592</APP_VAL>
      <TERM>180</TERM>
      <CLASSIFICATION>UNKNOWN</CLASSIFICATION>
      <IDENTIFIER>N_APPL05286019_NHOU</IDENTIFIER>
      <PRODUCT>NHL_IND</PRODUCT>
      <DATE>2023-09-13</DATE>
      <APP_DTE>2023-09-13</APP_DTE>
      <BRNCH_RGN>Yamuna Nagar</BRNCH_RGN>
      <MA>
        <PAN>CHIPR7239H</PAN>
        <FST_NME>RAJNI</FST_NME>
        <LST_NME>RAJNI</LST_NME>
        <DOB>1982-07-18</DOB>
        <AGE>41</AGE>
        <GNDR>FEMALE</GNDR>
        <MA_CA>
          <ADD>W O RAJKUMAR,MARWA KALAN MARWA KALAN</ADD>
          <CTY>Yamuna Nagar</CTY>
          <STE>Haryana</STE>
          <CTRY>India</CTRY>
          <PIN>135102</PIN>
        </MA_CA>
        <MA_PMA>
          <ADD>W O RAJKUMAR,MARWA KALAN MARWA KALAN</ADD>
          <CTY>Yamuna Nagar</CTY>
          <STE>Haryana</STE>
          <CTRY>India</CTRY>
          <PIN>135102</PIN>
        </MA_PMA>
        <MA_MT>
          <TEL_NO>8930158387</TEL_NO>
        </MA_MT>
        <MA_EMP>
          <ORG_NME>SHREE KRISHANA GARMENT</ORG_NME>
          <EMP_IND>OTHER</EMP_IND>
          <MA_EMP_AD>
            <ADD>WO RAJKUMAR, 283,MARWAN KALAN, YAMUNANAGAR </ADD>
            <CTY>Yamuna Nagar</CTY>
            <STE>Haryana</STE>
            <CTRY>India</CTRY>
            <PIN>135102</PIN>
          </MA_EMP_AD>
          <MA_EMP_BT>
            <TEL_NO>8930158387</TEL_NO>
          </MA_EMP_BT>
        </MA_EMP>
      </MA>
      <JA>
        <PAN>GGCPR6919B</PAN>
        <FST_NME>RAJKUMAR</FST_NME>
        <LST_NME>RAJKUMAR</LST_NME>
        <DOB>1981-01-01</DOB>
        <AGE>42</AGE>
        <GNDR>MALE</GNDR>
        <JA_CA>
          <ADD>S O JARNAIL SINGH,MARWA KALAN 283 MARWA KALAN</ADD>
          <CTY>Yamuna Nagar</CTY>
          <STE>Haryana</STE>
          <CTRY>India</CTRY>
          <PIN>135102</PIN>
        </JA_CA>
      </JA>
      <RF>
        <FST_NME>RENU</FST_NME>
        <LST_NME>BALA</LST_NME>
        <RF_MT>
          <TEL_NO>8053870169</TEL_NO>
        </RF_MT>
      </RF>
      <RF>
        <FST_NME>SUKHBIR</FST_NME>
        <RF_MT>
          <TEL_NO>8053870169</TEL_NO>
        </RF_MT>
      </RF>
    </SUBMISSION>
    <SUBMISSION>
      <APP_VAL>936736</APP_VAL>
      <TERM>180</TERM>
      <CLASSIFICATION>UNKNOWN</CLASSIFICATION>
      <IDENTIFIER>N_APPL05285920_HOU</IDENTIFIER>
      <PRODUCT>HL_IND</PRODUCT>
      <DATE>2023-09-13</DATE>
      <APP_DTE>2023-09-13</APP_DTE>
      <BRNCH_RGN>Yamuna Nagar</BRNCH_RGN>
      <MA>
        <PAN>ISNPK9735D</PAN>
        <FST_NME>JAMIL</FST_NME>
        <LST_NME>KHAN</LST_NME>
        <DOB>1979-01-29</DOB>
        <AGE>44</AGE>
        <GNDR>MALE</GNDR>
        <MA_CA>
          <ADD>S O BABU RAM,55,MAIN GALIPOLI</ADD>
          <CTY>Yamuna Nagar</CTY>
          <STE>Haryana</STE>
          <CTRY>India</CTRY>
          <PIN>135133</PIN>
        </MA_CA>
        <MA_PMA>
          <ADD>S O BABU RAM,55,MAIN GALIPOLI</ADD>
          <CTY>Yamuna Nagar</CTY>
          <STE>Haryana</STE>
          <CTRY>India</CTRY>
          <PIN>135133</PIN>
        </MA_PMA>
        <MA_MT>
          <TEL_NO>9306438371</TEL_NO>
        </MA_MT>
        <MA_EMP>
          <ORG_NME>JAMIL AUTO RICKSHAW</ORG_NME>
          <EMP_IND>TRAVEL</EMP_IND>
          <MA_EMP_AD>
            <ADD>VILL POTLIYAMUNANAGAR </ADD>
            <CTY>Yamuna Nagar</CTY>
            <STE>Haryana</STE>
            <CTRY>India</CTRY>
            <PIN>135133</PIN>
          </MA_EMP_AD>
          <MA_EMP_BT>
            <TEL_NO>9306438371</TEL_NO>
          </MA_EMP_BT>
        </MA_EMP>
      </MA>
      <JA>
        <PAN>CNDPV9151K</PAN>
        <FST_NME>VASHILA</FST_NME>
        <LST_NME>VASHILA</LST_NME>
        <DOB>1982-01-01</DOB>
        <AGE>41</AGE>
        <GNDR>FEMALE</GNDR>
        <JA_CA>
          <ADD>W OJAMIL KHAN,POTLI 16 KAMUNA NAGAR,KHURDBAN</ADD>
          <CTY>Yamuna Nagar</CTY>
          <STE>Haryana</STE>
          <CTRY>India</CTRY>
          <PIN>135133</PIN>
        </JA_CA>
      </JA>
      <RF>
        <FST_NME>FARMID</FST_NME>
        <LST_NME>KHAN</LST_NME>
        <RF_MT>
          <TEL_NO>9813758458</TEL_NO>
        </RF_MT>
      </RF>
      <RF>
        <FST_NME>SAMSU</FST_NME>
        <RF_MT>
          <TEL_NO>9813758458</TEL_NO>
        </RF_MT>
      </RF>
    </SUBMISSION>
    <SUBMISSION>
      <APP_VAL>534113</APP_VAL>
      <TERM>180</TERM>
      <CLASSIFICATION>UNKNOWN</CLASSIFICATION>
      <IDENTIFIER>N_APPL05286049_NHOU</IDENTIFIER>
      <PRODUCT>NHL_IND</PRODUCT>
      <DATE>2023-09-13</DATE>
      <APP_DTE>2023-09-13</APP_DTE>
      <BRNCH_RGN>LALITPUR</BRNCH_RGN>
      <MA>
        <PAN>KXCPK7889G</PAN>
        <FST_NME>ASHOK</FST_NME>
        <LST_NME>KUMAR</LST_NME>
        <DOB>1978-01-01</DOB>
        <AGE>45</AGE>
        <GNDR>MALE</GNDR>
        <MA_CA>
          <ADD>AARA MACHINE KE PAS JAKHORA</ADD>
          <CTY>Lalitpur</CTY>
          <STE>Uttar Pradesh</STE>
          <CTRY>India</CTRY>
          <PIN>284403</PIN>
        </MA_CA>
        <MA_PMA>
          <ADD>AARA MACHINE KE PAS JAKHORA</ADD>
          <CTY>Lalitpur</CTY>
          <STE>Uttar Pradesh</STE>
          <CTRY>India</CTRY>
          <PIN>284403</PIN>
        </MA_PMA>
        <MA_MT>
          <TEL_NO>8081872539</TEL_NO>
        </MA_MT>
        <MA_BNK>
          <BNK_NM>STATE BANK OF INDIA</BNK_NM>
          <ACC_NO>7920</ACC_NO>
        </MA_BNK>
        <MA_EMP>
          <ORG_NME>Surendra Boot House</ORG_NME>
          <EMP_IND>OTHER</EMP_IND>
          <MA_EMP_AD>
            <ADD>BUS STAND KE PASJAKHORA</ADD>
            <CTY>Lalitpur</CTY>
            <STE>Uttar Pradesh</STE>
            <CTRY>India</CTRY>
            <PIN>284403</PIN>
          </MA_EMP_AD>
          <MA_EMP_BT>
            <TEL_NO>8081872539</TEL_NO>
          </MA_EMP_BT>
        </MA_EMP>
      </MA>
      <JA>
        <PAN>LUCPS8818M</PAN>
        <FST_NME>RISHABH</FST_NME>
        <LST_NME>SAHU</LST_NME>
        <DOB>2002-09-25</DOB>
        <AGE>20</AGE>
        <GNDR>MALE</GNDR>
        <JA_CA>
          <ADD>AARA MACHINE KE PASJAKHORALALITPUR </ADD>
          <CTY>Lalitpur</CTY>
          <STE>Uttar Pradesh</STE>
          <CTRY>India</CTRY>
          <PIN>284126</PIN>
        </JA_CA>
      </JA>
      <JA>
        <FST_NME>SUNITA</FST_NME>
        <LST_NME>SUNITA</LST_NME>
        <DOB>1980-01-01</DOB>
        <AGE>43</AGE>
        <GNDR>FEMALE</GNDR>
        <JA_CA>
          <ADD>AARA MACHINE KE PASSJAKHORA </ADD>
          <CTY>Lalitpur</CTY>
          <STE>Uttar Pradesh</STE>
          <CTRY>India</CTRY>
          <PIN>284126</PIN>
        </JA_CA>
      </JA>
      <RF>
        <FST_NME>CHHOTU</FST_NME>
        <RF_MT>
          <TEL_NO>8604253010</TEL_NO>
        </RF_MT>
      </RF>
      <RF>
        <FST_NME>SHARDA</FST_NME>
        <RF_MT>
          <TEL_NO>8604253010</TEL_NO>
        </RF_MT>
      </RF>
    </SUBMISSION>
    <SUBMISSION>
      <APP_VAL>980271</APP_VAL>
      <TERM>144</TERM>
      <CLASSIFICATION>UNKNOWN</CLASSIFICATION>
      <IDENTIFIER>S_APPL05275048_NHOU</IDENTIFIER>
      <PRODUCT>NHL_IND</PRODUCT>
      <DATE>2023-09-13</DATE>
      <APP_DTE>2023-09-13</APP_DTE>
      <BRNCH_RGN>KARIMNAGAR</BRNCH_RGN>
      <MA>
        <PAN>JHBPK9406H</PAN>
        <FST_NME>KAMPELLY</FST_NME>
        <LST_NME>ANILKUMAR</LST_NME>
        <DOB>1989-06-02</DOB>
        <AGE>34</AGE>
        <GNDR>MALE</GNDR>
        <MA_CA>
          <ADD>S O KAMPELLY MALLESHAM,H NO 6-3-175,DURGAMMA GADDA</ADD>
          <CTY>Karimnagar</CTY>
          <STE>Telangana</STE>
          <CTRY>India</CTRY>
          <PIN>505001</PIN>
        </MA_CA>
        <MA_PMA>
          <ADD>S O KAMPELLY MALLESHAM,H NO 6-3-175,DURGAMMA GADDA</ADD>
          <CTY>Karimnagar</CTY>
          <STE>Telangana</STE>
          <CTRY>India</CTRY>
          <PIN>505001</PIN>
        </MA_PMA>
        <MA_MT>
          <TEL_NO>8688964214</TEL_NO>
        </MA_MT>
        <MA_BNK>
          <BNK_NM>STATE BANK OF HYDERABAD</BNK_NM>
          <ACC_NO>62224307211</ACC_NO>
        </MA_BNK>
      </MA>
      <JA>
        <PAN>MFNPK0436C</PAN>
        <FST_NME>KAMPALLI</FST_NME>
        <LST_NME>MALLESHAM</LST_NME>
        <DOB>1970-01-01</DOB>
        <AGE>53</AGE>
        <GNDR>MALE</GNDR>
        <JA_CA>
          <ADD>S O KAMPELLI POCHAIAH,H NO 6-3-175,DURGAMMA GADDA</ADD>
          <CTY>Karimnagar</CTY>
          <STE>Telangana</STE>
          <CTRY>India</CTRY>
          <PIN>505001</PIN>
        </JA_CA>
      </JA>
      <JA>
        <PAN>JJRPK7214M</PAN>
        <FST_NME>KAMPALLY</FST_NME>
        <LST_NME>LAXMI</LST_NME>
        <DOB>1974-01-01</DOB>
        <AGE>49</AGE>
        <GNDR>FEMALE</GNDR>
        <JA_CA>
          <ADD>W O KAMPELLY MALLESHAM,H NO 6-3-175 DURGAMMA GADDA</ADD>
          <CTY>Karimnagar</CTY>
          <STE>Telangana</STE>
          <CTRY>India</CTRY>
          <PIN>505001</PIN>
        </JA_CA>
      </JA>
      <RF>
        <FST_NME>NARESH</FST_NME>
        <RF_MT>
          <TEL_NO>9700320414</TEL_NO>
        </RF_MT>
      </RF>
      <RF>
        <FST_NME>AJAY</FST_NME>
        <RF_MT>
          <TEL_NO>9700320414</TEL_NO>
        </RF_MT>
      </RF>
    </SUBMISSION>
  </SUBMISSIONS>
</BATCH>
