<?xml version="1.0" encoding="UTF-8" standalone="no"?>
<BATCH xmlns="urn:mclsoftware.co.uk:hunterII" xmlns:xsd="http://www.w3.org/2001/XMLSchema" xmlns:xsi="http://www.w3.org/2001/XMLSchema-instance">
  <HEADER>
    <COUNT>32</COUNT>
    <ORIGINATOR>SHDFC</ORIGINATOR>
  </HEADER>
  <SUBMISSIONS>
    <SUBMISSION>
      <APP_VAL>2895494</APP_VAL>
      <TERM>240</TERM>
      <CLASSIFICATION>UNKNOWN</CLASSIFICATION>
      <IDENTIFIER>N_APPL05301492_HOU</IDENTIFIER>
      <PRODUCT>HL_IND</PRODUCT>
      <DATE>2023-11-17</DATE>
      <APP_DTE>2023-11-17</APP_DTE>
      <BRNCH_RGN>Delhi</BRNCH_RGN>
      <MA>
        <PAN>BNYPA7945L</PAN>
        <FST_NME>AMANDEEP</FST_NME>
        <LST_NME>AMANDEEP</LST_NME>
        <DOB>1992-10-03</DOB>
        <AGE>31</AGE>
        <GNDR>MALE</GNDR>
        <MA_CA>
          <ADD>F 27 2ND FLOOR LEFT SIDE JEEWAN PARK UTTAM NAGARF 27 2ND FLOOR LEFT SIDE JEEWAN PARK UTTAM NAGARWEST</ADD>
          <CTY>West Delhi</CTY>
          <STE>Delhi</STE>
          <CTRY>India</CTRY>
          <PIN>110059</PIN>
        </MA_CA>
        <MA_PMA>
          <ADD>F 27 2ND FLOOR LEFT SIDE JEEWAN PARK UTTAM NAGARF 27 2ND FLOOR LEFT SIDE JEEWAN PARK UTTAM NAGARWEST</ADD>
          <CTY>West Delhi</CTY>
          <STE>Delhi</STE>
          <CTRY>India</CTRY>
          <PIN>110059</PIN>
        </MA_PMA>
        <MA_MT>
          <TEL_NO>9990879821</TEL_NO>
        </MA_MT>
        <MA_BNK>
          <BNK_NM>PUNJAB NATIONAL BANK</BNK_NM>
          <ACC_NO>0419</ACC_NO>
        </MA_BNK>
        <MA_EMP>
          <ORG_NME>REDISSION</ORG_NME>
          <EMP_IND>FOOD</EMP_IND>
          <MA_EMP_AD>
            <ADD>REDISSIN GURGAON UDYOG VIHAR</ADD>
            <CTY>Gurgaon</CTY>
            <STE>Haryana</STE>
            <CTRY>India</CTRY>
            <PIN>122016</PIN>
          </MA_EMP_AD>
          <MA_EMP_BT>
            <TEL_NO>9990879821</TEL_NO>
          </MA_EMP_BT>
        </MA_EMP>
      </MA>
      <JA>
        <PAN>BDWPN7778N</PAN>
        <FST_NME>NISHA</FST_NME>
        <LST_NME>SINGH</LST_NME>
        <DOB>1994-11-16</DOB>
        <AGE>29</AGE>
        <GNDR>FEMALE</GNDR>
        <JA_CA>
          <ADD>F 27 2ND FLOOR LEFT SIDE JEEWAN PARK UTTAM NAGAR,WEST</ADD>
          <CTY>West Delhi</CTY>
          <STE>Delhi</STE>
          <CTRY>India</CTRY>
          <PIN>110059</PIN>
        </JA_CA>
      </JA>
      <JA>
        <PAN>BBVPN4706M</PAN>
        <FST_NME>KUNAL</FST_NME>
        <LST_NME>NIRALA</LST_NME>
        <DOB>1997-04-07</DOB>
        <AGE>26</AGE>
        <GNDR>MALE</GNDR>
        <JA_CA>
          <ADD>MAHIRAJ,F-27 SECOND FLOOR,LEFT SIDEJEEWAN PARK,NEAR FAMILY HOSPITAL,UTTAM NAGARJEEVAN PARK,WEST</ADD>
          <CTY>West Delhi</CTY>
          <STE>Delhi</STE>
          <CTRY>India</CTRY>
          <PIN>110059</PIN>
        </JA_CA>
      </JA>
      <BR>
        <ORG_CD>5920</ORG_CD>
        <ORG_NME>Andromeda Sales And Distribution PVT LTD</ORG_NME>
        <BR_ADD>
          <ADD>Ground Floor, H no.1-19-4, Sriram Nagar, East Godavari District, East Godavari, Andhra Pradesh </ADD>
          <CTY>Navi Mumbai</CTY>
          <STE>Maharashtra</STE>
          <PIN>401202</PIN>
          <CTRY>INDIA</CTRY>
        </BR_ADD>
      </BR>
      <RF>
        <FST_NME>RAHUL</FST_NME>
        <RF_MT>
          <TEL_NO>9711519427</TEL_NO>
        </RF_MT>
      </RF>
      <RF>
        <FST_NME>SANDEEP</FST_NME>
        <LST_NME>MOHAN</LST_NME>
        <RF_MT>
          <TEL_NO>9711519427</TEL_NO>
        </RF_MT>
      </RF>
    </SUBMISSION>
    <SUBMISSION>
      <APP_VAL>871457</APP_VAL>
      <TERM>180</TERM>
      <CLASSIFICATION>UNKNOWN</CLASSIFICATION>
      <IDENTIFIER>W_APPL05295515_NHOU</IDENTIFIER>
      <PRODUCT>NHL_IND</PRODUCT>
      <DATE>2023-11-17</DATE>
      <APP_DTE>2023-11-17</APP_DTE>
      <BRNCH_RGN>Gujarat</BRNCH_RGN>
      <MA>
        <PAN>BBCPR7351H</PAN>
        <FST_NME>RAJPUT</FST_NME>
        <MID_NME>KRISHANAKANT</MID_NME>
        <LST_NME>RAJPUT</LST_NME>
        <DOB>1982-11-05</DOB>
        <AGE>41</AGE>
        <GNDR>MALE</GNDR>
        <MA_CA>
          <ADD>202 C,45417 2,80,BHAGWAT ALIGANCE NEAR OMSHANTINAGAR 2NANI CANAL ROAD,NAROL</ADD>
          <CTY>Ahmedabad</CTY>
          <STE>Gujarat</STE>
          <CTRY>India</CTRY>
          <PIN>382405</PIN>
        </MA_CA>
        <MA_PMA>
          <ADD>202 C,45417 2,80,BHAGWAT ALIGANCE NEAR OMSHANTINAGAR 2NANI CANAL ROAD,NAROL</ADD>
          <CTY>Ahmedabad</CTY>
          <STE>Gujarat</STE>
          <CTRY>India</CTRY>
          <PIN>382405</PIN>
        </MA_PMA>
        <MA_MT>
          <TEL_NO>9327447515</TEL_NO>
        </MA_MT>
        <MA_EMP>
          <ORG_NME>''Mahakali Garment''</ORG_NME>
          <EMP_IND>OTHER</EMP_IND>
          <MA_EMP_AD>
            <ADD>202 C, BHAGWAT ALIGANCE,NEAR OMSHANTINAGAR-2,NANI CANAL ROAD,NAROL</ADD>
            <CTY>Ahmedabad</CTY>
            <STE>Gujarat</STE>
            <CTRY>India</CTRY>
            <PIN>382405</PIN>
          </MA_EMP_AD>
          <MA_EMP_BT>
            <TEL_NO>9327447515</TEL_NO>
          </MA_EMP_BT>
        </MA_EMP>
      </MA>
      <JA>
        <PAN>BRAPR9506A</PAN>
        <FST_NME>RAJPUT</FST_NME>
        <MID_NME>PRITIBEN</MID_NME>
        <LST_NME>PRITIBEN</LST_NME>
        <DOB>1993-07-30</DOB>
        <AGE>30</AGE>
        <GNDR>FEMALE</GNDR>
        <JA_CA>
          <ADD>202 C,45417 2,80,BHAGWAT ALIGANCE NEAR OMSHANTINAGAR 2NANI CANAL ROAD,NAROL</ADD>
          <CTY>Ahmedabad</CTY>
          <STE>Gujarat</STE>
          <CTRY>India</CTRY>
          <PIN>382405</PIN>
        </JA_CA>
      </JA>
      <RF>
        <FST_NME>PIYUSH</FST_NME>
        <LST_NME>THAKKAR</LST_NME>
        <RF_MT>
          <TEL_NO>9978991001</TEL_NO>
        </RF_MT>
      </RF>
      <RF>
        <FST_NME>RAVI</FST_NME>
        <LST_NME>YADAV</LST_NME>
        <RF_MT>
          <TEL_NO>9978991001</TEL_NO>
        </RF_MT>
      </RF>
    </SUBMISSION>
    <SUBMISSION>
      <APP_VAL>1498689</APP_VAL>
      <TERM>180</TERM>
      <CLASSIFICATION>UNKNOWN</CLASSIFICATION>
      <IDENTIFIER>W_APPL05291818_NHOU</IDENTIFIER>
      <PRODUCT>NHL_IND</PRODUCT>
      <DATE>2023-11-17</DATE>
      <APP_DTE>2023-11-17</APP_DTE>
      <BRNCH_RGN>Gujarat</BRNCH_RGN>
      <MA>
        <PAN>ALLPR8088F</PAN>
        <FST_NME>RAVAL</FST_NME>
        <MID_NME>NIRAV</MID_NME>
        <LST_NME>RAVAL</LST_NME>
        <DOB>1980-08-19</DOB>
        <AGE>43</AGE>
        <GNDR>MALE</GNDR>
        <MA_CA>
          <ADD>42,4,PRERNA TENAMENT PARASNAGAR,VATVA CROSS ROAD ISANPUR AHMEDABAD </ADD>
          <CTY>Ahmedabad</CTY>
          <STE>Gujarat</STE>
          <CTRY>India</CTRY>
          <PIN>382443</PIN>
        </MA_CA>
        <MA_PMA>
          <ADD>42,4,PRERNA TENAMENT PARASNAGAR,VATVA CROSS ROAD ISANPUR AHMEDABAD </ADD>
          <CTY>Ahmedabad</CTY>
          <STE>Gujarat</STE>
          <CTRY>India</CTRY>
          <PIN>382443</PIN>
        </MA_PMA>
        <MA_MT>
          <TEL_NO>9724417294</TEL_NO>
        </MA_MT>
      </MA>
      <JA>
        <PAN>AAKPO6571G</PAN>
        <FST_NME>HINA</FST_NME>
        <MID_NME>NIRAV</MID_NME>
        <LST_NME>RAVAL</LST_NME>
        <DOB>1979-11-09</DOB>
        <AGE>44</AGE>
        <GNDR>FEMALE</GNDR>
        <JA_CA>
          <ADD>42,4,PRERNA TENAMENT PARASNAGAR,VATVA CROSS ROAD ISANPUR AHMEDABAD </ADD>
          <CTY>Ahmedabad</CTY>
          <STE>Gujarat</STE>
          <CTRY>India</CTRY>
          <PIN>382443</PIN>
        </JA_CA>
      </JA>
      <RF>
        <FST_NME>PRITESH</FST_NME>
        <LST_NME>SONI</LST_NME>
        <RF_MT>
          <TEL_NO>9725538364</TEL_NO>
        </RF_MT>
      </RF>
      <RF>
        <FST_NME>NIMESH</FST_NME>
        <LST_NME>DODIYA</LST_NME>
        <RF_MT>
          <TEL_NO>9725538364</TEL_NO>
        </RF_MT>
      </RF>
    </SUBMISSION>
    <SUBMISSION>
      <APP_VAL>580416</APP_VAL>
      <TERM>240</TERM>
      <CLASSIFICATION>UNKNOWN</CLASSIFICATION>
      <IDENTIFIER>N_APPL05300771_HOU</IDENTIFIER>
      <PRODUCT>HL_IND</PRODUCT>
      <DATE>2023-11-17</DATE>
      <APP_DTE>2023-11-17</APP_DTE>
      <BRNCH_RGN>UP - Agra</BRNCH_RGN>
      <MA>
        <PAN>EMAPK3226E</PAN>
        <FST_NME>DINESH</FST_NME>
        <LST_NME>KUSHWAH</LST_NME>
        <DOB>1983-01-01</DOB>
        <AGE>40</AGE>
        <GNDR>MALE</GNDR>
        <MA_CA>
          <ADD>S O,HET SINGH,12A 26DPRAKASH NAGAR,NUNIHAI</ADD>
          <CTY>Agra</CTY>
          <STE>Uttar Pradesh</STE>
          <CTRY>India</CTRY>
          <PIN>282006</PIN>
        </MA_CA>
        <MA_PMA>
          <ADD>S O,HET SINGH,12A 26DPRAKASH NAGAR,NUNIHAI</ADD>
          <CTY>Agra</CTY>
          <STE>Uttar Pradesh</STE>
          <CTRY>India</CTRY>
          <PIN>282006</PIN>
        </MA_PMA>
        <MA_MT>
          <TEL_NO>9528824293</TEL_NO>
        </MA_MT>
        <MA_EMA>
          <EMA_ADD>KUSHWAHAKSHAY13@GMAIL.COM</EMA_ADD>
        </MA_EMA>
        <MA_BNK>
          <BNK_NM>STATE BANK OF INDIA</BNK_NM>
          <ACC_NO>20310825012</ACC_NO>
        </MA_BNK>
        <MA_EMP>
          <ORG_NME>SHANTI ENGINEARING WORKS</ORG_NME>
          <EMP_IND>OTHER</EMP_IND>
          <MA_EMP_AD>
            <ADD>PRAKASH NAGAR NUNIHAI RAMBAGH  AGRA</ADD>
            <CTY>Agra</CTY>
            <STE>Uttar Pradesh</STE>
            <CTRY>India</CTRY>
            <PIN>282006</PIN>
          </MA_EMP_AD>
          <MA_EMP_BT>
            <TEL_NO>9528824293</TEL_NO>
          </MA_EMP_BT>
        </MA_EMP>
      </MA>
      <JA>
        <PAN>KFHPK1286L</PAN>
        <FST_NME>AKSHYA</FST_NME>
        <LST_NME>KUSHWAH</LST_NME>
        <DOB>2002-10-09</DOB>
        <AGE>21</AGE>
        <GNDR>MALE</GNDR>
        <JA_CA>
          <ADD>C O DINESH KUSHWAH,12A 260,PRAKASH NAGARNUNHAI</ADD>
          <CTY>Agra</CTY>
          <STE>Uttar Pradesh</STE>
          <CTRY>India</CTRY>
          <PIN>282006</PIN>
        </JA_CA>
      </JA>
      <RF>
        <FST_NME>SANJAY</FST_NME>
        <RF_MT>
          <TEL_NO>8273239572</TEL_NO>
        </RF_MT>
      </RF>
      <RF>
        <FST_NME>UDHAY</FST_NME>
        <LST_NME>SINGH</LST_NME>
        <RF_MT>
          <TEL_NO>8273239572</TEL_NO>
        </RF_MT>
      </RF>
    </SUBMISSION>
    <SUBMISSION>
      <APP_VAL>544661</APP_VAL>
      <TERM>180</TERM>
      <CLASSIFICATION>UNKNOWN</CLASSIFICATION>
      <IDENTIFIER>N_APPL05300369_NHOU</IDENTIFIER>
      <PRODUCT>NHL_IND</PRODUCT>
      <DATE>2023-11-17</DATE>
      <APP_DTE>2023-11-17</APP_DTE>
      <BRNCH_RGN>UP - Agra</BRNCH_RGN>
      <MA>
        <PAN>BMJPS1298A</PAN>
        <FST_NME>JANG</FST_NME>
        <MID_NME>BAHADUR</MID_NME>
        <LST_NME>SINGH</LST_NME>
        <DOB>1981-09-12</DOB>
        <AGE>42</AGE>
        <GNDR>MALE</GNDR>
        <MA_CA>
          <ADD>S O MALKHAN SINGH,21 58 FLAT NO 8 FIRST FLOOR,RAMODEVI MARKET FREE GANJ ROADBELANGANJ,BELAN GANJ</ADD>
          <CTY>Agra</CTY>
          <STE>Uttar Pradesh</STE>
          <CTRY>India</CTRY>
          <PIN>282004</PIN>
        </MA_CA>
        <MA_PMA>
          <ADD>S O MALKHAN SINGH,21 58 FLAT NO 8 FIRST FLOOR,RAMODEVI MARKET FREE GANJ ROADBELANGANJ,BELAN GANJ</ADD>
          <CTY>Agra</CTY>
          <STE>Uttar Pradesh</STE>
          <CTRY>India</CTRY>
          <PIN>282004</PIN>
        </MA_PMA>
        <MA_PROP>
          <ADD>H.NO-21158, RAMADEVI MARKET FREEGANJ AGRA-282001</ADD>
          <CTY>Agra</CTY>
          <STE>Uttar Pradesh</STE>
          <CTRY>India</CTRY>
          <PIN>282001</PIN>
        </MA_PROP>
        <MA_MT>
          <TEL_NO>8077930025</TEL_NO>
        </MA_MT>
        <MA_BNK>
          <BNK_NM>PUNJAB NATIONAL BANK</BNK_NM>
          <ACC_NO>3000100173012</ACC_NO>
        </MA_BNK>
        <MA_EMP>
          <ORG_NME>Triveni Tour and Travels</ORG_NME>
          <EMP_IND>TRAVEL</EMP_IND>
          <MA_EMP_AD>
            <ADD>RAMODEVI FREEGANJ AGRA</ADD>
            <CTY>Agra</CTY>
            <STE>Uttar Pradesh</STE>
            <CTRY>India</CTRY>
            <PIN>282004</PIN>
          </MA_EMP_AD>
          <MA_EMP_BT>
            <TEL_NO>8077930025</TEL_NO>
          </MA_EMP_BT>
        </MA_EMP>
      </MA>
      <JA>
        <PAN>CPDPB8910E</PAN>
        <FST_NME>TRIVENI</FST_NME>
        <LST_NME>BHADAURIYA</LST_NME>
        <DOB>1989-04-16</DOB>
        <AGE>34</AGE>
        <GNDR>FEMALE</GNDR>
        <JA_CA>
          <ADD>W O JANG BEHADUR SINGH,21 58 FLAT NO 8 FIRST FLOOR,RAMODEVI MARKET FREE GANJ ROADBELANGANJ,BELAN GANJ</ADD>
          <CTY>Agra</CTY>
          <STE>Uttar Pradesh</STE>
          <CTRY>India</CTRY>
          <PIN>282004</PIN>
        </JA_CA>
      </JA>
      <RF>
        <FST_NME>VIJAY</FST_NME>
        <LST_NME>SHARMA</LST_NME>
        <RF_MT>
          <TEL_NO>7417294346</TEL_NO>
        </RF_MT>
      </RF>
      <RF>
        <FST_NME>HARSH</FST_NME>
        <LST_NME>TOMAR</LST_NME>
        <RF_MT>
          <TEL_NO>7417294346</TEL_NO>
        </RF_MT>
      </RF>
    </SUBMISSION>
    <SUBMISSION>
      <APP_VAL>881340</APP_VAL>
      <TERM>180</TERM>
      <CLASSIFICATION>UNKNOWN</CLASSIFICATION>
      <IDENTIFIER>N_APPL05298930_HOU</IDENTIFIER>
      <PRODUCT>HL_IND</PRODUCT>
      <DATE>2023-11-17</DATE>
      <APP_DTE>2023-11-17</APP_DTE>
      <BRNCH_RGN>Delhi</BRNCH_RGN>
      <MA>
        <PAN>FDDPS7928Q</PAN>
        <FST_NME>RAMU</FST_NME>
        <LST_NME>SINGH</LST_NME>
        <DOB>1987-01-15</DOB>
        <AGE>36</AGE>
        <GNDR>MALE</GNDR>
        <MA_CA>
          <ADD>S O KESWAR SINGH,F-927,GAJIPUR ROADUTTAM NAGAR DABUA COLONY</ADD>
          <CTY>Faridabad</CTY>
          <STE>Haryana</STE>
          <CTRY>India</CTRY>
          <PIN>121001</PIN>
        </MA_CA>
        <MA_PMA>
          <ADD>S O KESWAR SINGH,F-927,GAJIPUR ROADUTTAM NAGAR DABUA COLONY</ADD>
          <CTY>Faridabad</CTY>
          <STE>Haryana</STE>
          <CTRY>India</CTRY>
          <PIN>121001</PIN>
        </MA_PMA>
        <MA_PROP>
          <ADD>dummydummydummy</ADD>
          <CTY>Faridabad</CTY>
          <STE>Haryana</STE>
          <CTRY>India</CTRY>
          <PIN>121003</PIN>
        </MA_PROP>
        <MA_MT>
          <TEL_NO>9999093169</TEL_NO>
        </MA_MT>
        <MA_EMP>
          <ORG_NME>BRITE BROTHERS LIMITED</ORG_NME>
          <EMP_IND>OTHER</EMP_IND>
          <MA_EMP_AD>
            <ADD>SECTOR 55 NEAR BY ATUL COMPANY FARIDABADHARYANA</ADD>
            <CTY>Faridabad</CTY>
            <STE>Haryana</STE>
            <CTRY>India</CTRY>
            <PIN>121001</PIN>
          </MA_EMP_AD>
          <MA_EMP_BT>
            <TEL_NO>9999093169</TEL_NO>
          </MA_EMP_BT>
        </MA_EMP>
      </MA>
      <JA>
        <PAN>FFEPD2384N</PAN>
        <FST_NME>SONI</FST_NME>
        <LST_NME>DEVI</LST_NME>
        <DOB>1989-10-15</DOB>
        <AGE>34</AGE>
        <GNDR>FEMALE</GNDR>
        <JA_CA>
          <ADD>HOUSE NO 927 GAJIPUR ROAD UTTAM NAGAR DABUA COLONY FARIDABADHARYANA</ADD>
          <CTY>Faridabad</CTY>
          <STE>Haryana</STE>
          <CTRY>India</CTRY>
          <PIN>121001</PIN>
        </JA_CA>
      </JA>
      <RF>
        <FST_NME>DINESH</FST_NME>
        <LST_NME>KUMAR</LST_NME>
        <RF_MT>
          <TEL_NO>9717197420</TEL_NO>
        </RF_MT>
      </RF>
      <RF>
        <FST_NME>ASHOK</FST_NME>
        <LST_NME>KUMAR</LST_NME>
        <RF_MT>
          <TEL_NO>9717197420</TEL_NO>
        </RF_MT>
      </RF>
    </SUBMISSION>
    <SUBMISSION>
      <APP_VAL>329130</APP_VAL>
      <TERM>120</TERM>
      <CLASSIFICATION>UNKNOWN</CLASSIFICATION>
      <IDENTIFIER>N_APPL05298893_NHOU</IDENTIFIER>
      <PRODUCT>NHL_IND</PRODUCT>
      <DATE>2023-11-17</DATE>
      <APP_DTE>2023-11-17</APP_DTE>
      <BRNCH_RGN>Punjab</BRNCH_RGN>
      <MA>
        <PAN>NWLPS7286C</PAN>
        <FST_NME>GAGANDEEP</FST_NME>
        <LST_NME>SINGH</LST_NME>
        <DOB>2001-09-10</DOB>
        <AGE>22</AGE>
        <GNDR>MALE</GNDR>
        <MA_CA>
          <ADD>S O BUNTI SINGH SUNAM ROAD MEHLAN SANGRUR PUNJAB</ADD>
          <CTY>Sangrur</CTY>
          <STE>Punjab</STE>
          <CTRY>India</CTRY>
          <PIN>148001</PIN>
        </MA_CA>
        <MA_PMA>
          <ADD>S O BUNTI SINGH SUNAM ROAD MEHLAN SANGRUR PUNJAB</ADD>
          <CTY>Sangrur</CTY>
          <STE>Punjab</STE>
          <CTRY>India</CTRY>
          <PIN>148001</PIN>
        </MA_PMA>
        <MA_MT>
          <TEL_NO>9041920378</TEL_NO>
        </MA_MT>
        <MA_EMP>
          <ORG_NME>KHARA AGRO CENTRE </ORG_NME>
          <EMP_IND>OTHER</EMP_IND>
          <MA_EMP_AD>
            <ADD>NAGRI ROADMEHLAN CHOWK</ADD>
            <CTY>Sangrur</CTY>
            <STE>Punjab</STE>
            <CTRY>India</CTRY>
            <PIN>148001</PIN>
          </MA_EMP_AD>
          <MA_EMP_BT>
            <TEL_NO>9041920378</TEL_NO>
          </MA_EMP_BT>
        </MA_EMP>
      </MA>
      <JA>
        <FST_NME>BUNTI</FST_NME>
        <LST_NME>SINGH</LST_NME>
        <DOB>1970-10-23</DOB>
        <AGE>53</AGE>
        <GNDR>MALE</GNDR>
        <JA_CA>
          <ADD>S O CHANDI RAM KHADIAL ROAD TEHSIL SANGRUR MEHLAN PUNJAB</ADD>
          <CTY>Sangrur</CTY>
          <STE>Punjab</STE>
          <CTRY>India</CTRY>
          <PIN>148001</PIN>
        </JA_CA>
      </JA>
      <JA>
        <FST_NME>KRISHAN</FST_NME>
        <LST_NME>SINGH</LST_NME>
        <DOB>1981-01-01</DOB>
        <AGE>42</AGE>
        <GNDR>MALE</GNDR>
        <JA_CA>
          <ADD>S O CHANDI RAM HOUSE NUMBER 1202SUNAM ROAD VILL MEHLAN SANGRUR PUNJAB</ADD>
          <CTY>Sangrur</CTY>
          <STE>Punjab</STE>
          <CTRY>India</CTRY>
          <PIN>148001</PIN>
        </JA_CA>
      </JA>
      <RF>
        <FST_NME>MUKHTIAR</FST_NME>
        <LST_NME>SINGH</LST_NME>
        <RF_MT>
          <TEL_NO>9417637693</TEL_NO>
        </RF_MT>
      </RF>
      <RF>
        <FST_NME>RAJVIR</FST_NME>
        <LST_NME>SINGH</LST_NME>
        <RF_MT>
          <TEL_NO>9417637693</TEL_NO>
        </RF_MT>
      </RF>
    </SUBMISSION>
    <SUBMISSION>
      <APP_VAL>626922</APP_VAL>
      <TERM>180</TERM>
      <CLASSIFICATION>UNKNOWN</CLASSIFICATION>
      <IDENTIFIER>N_APPL05300930_NHOU</IDENTIFIER>
      <PRODUCT>NHL_IND</PRODUCT>
      <DATE>2023-11-17</DATE>
      <APP_DTE>2023-11-17</APP_DTE>
      <BRNCH_RGN>UP - Lucknow</BRNCH_RGN>
      <MA>
        <PAN>BRWPS6447M</PAN>
        <FST_NME>JITENDRA</FST_NME>
        <LST_NME>SINGH</LST_NME>
        <DOB>1974-06-10</DOB>
        <AGE>49</AGE>
        <GNDR>MALE</GNDR>
        <MA_CA>
          <ADD>C O NARENDRA PAL SINGH,00,DEV NAGARK.K.PURAM,IN FRONT OF AWASTHI FARM,SHUKLAGANJGANGAGHAT,MAJHARA PIPER KHERA GAIR EHATMALI</ADD>
          <CTY>Unnao</CTY>
          <STE>Uttar Pradesh</STE>
          <CTRY>India</CTRY>
          <PIN>209861</PIN>
        </MA_CA>
        <MA_PMA>
          <ADD>C O NARENDRA PAL SINGH,00,DEV NAGARK.K.PURAM,IN FRONT OF AWASTHI FARM,SHUKLAGANJGANGAGHAT,MAJHARA PIPER KHERA GAIR EHATMALI</ADD>
          <CTY>Unnao</CTY>
          <STE>Uttar Pradesh</STE>
          <CTRY>India</CTRY>
          <PIN>209861</PIN>
        </MA_PMA>
        <MA_MT>
          <TEL_NO>9889397460</TEL_NO>
        </MA_MT>
      </MA>
      <JA>
        <PAN>HHIPS3959G</PAN>
        <FST_NME>NEELAM</FST_NME>
        <LST_NME>SINGH</LST_NME>
        <DOB>1981-05-24</DOB>
        <AGE>42</AGE>
        <GNDR>FEMALE</GNDR>
        <JA_CA>
          <ADD>C O NARENDRA PAL SINGH,00,DEV NAGARK.K.PURAM,IN FRONT OF AWASTHI FARM,SHUKLAGANJGANGAGHAT,MAJHARA PIPER KHERA GAIR EHATMALI</ADD>
          <CTY>Unnao</CTY>
          <STE>Uttar Pradesh</STE>
          <CTRY>India</CTRY>
          <PIN>209861</PIN>
        </JA_CA>
      </JA>
      <RF>
        <FST_NME>ARVIND</FST_NME>
        <LST_NME>SINGH</LST_NME>
        <RF_MT>
          <TEL_NO>9506502577</TEL_NO>
        </RF_MT>
      </RF>
      <RF>
        <FST_NME>PRAMOD</FST_NME>
        <LST_NME>GIRI</LST_NME>
        <RF_MT>
          <TEL_NO>9506502577</TEL_NO>
        </RF_MT>
      </RF>
    </SUBMISSION>
    <SUBMISSION>
      <APP_VAL>461524</APP_VAL>
      <TERM>120</TERM>
      <CLASSIFICATION>UNKNOWN</CLASSIFICATION>
      <IDENTIFIER>N_APPL05299701_NHOU</IDENTIFIER>
      <PRODUCT>NHL_IND</PRODUCT>
      <DATE>2023-11-17</DATE>
      <APP_DTE>2023-11-17</APP_DTE>
      <BRNCH_RGN>UP - Agra</BRNCH_RGN>
      <MA>
        <PAN>CEOPP0309H</PAN>
        <FST_NME>RAVI</FST_NME>
        <LST_NME>PRAKASH</LST_NME>
        <DOB>1990-08-10</DOB>
        <AGE>33</AGE>
        <GNDR>MALE</GNDR>
        <MA_CA>
          <ADD>BIHARIPURA KALI MATA MANDIR K PASS JHANSI </ADD>
          <CTY>Jhansi</CTY>
          <STE>Uttar Pradesh</STE>
          <CTRY>India</CTRY>
          <PIN>284135</PIN>
        </MA_CA>
        <MA_PMA>
          <ADD>BIHARIPURA KALI MATA MANDIR K PASS JHANSI </ADD>
          <CTY>Jhansi</CTY>
          <STE>Uttar Pradesh</STE>
          <CTRY>India</CTRY>
          <PIN>284135</PIN>
        </MA_PMA>
        <MA_MT>
          <TEL_NO>8726259723</TEL_NO>
        </MA_MT>
        <MA_EMP>
          <ORG_NME>NATRAJ AUTOMOBILE</ORG_NME>
          <EMP_IND>OTHER</EMP_IND>
          <MA_EMP_AD>
            <ADD>GORAMACHIYA JHANSI </ADD>
            <CTY>Jhansi</CTY>
            <STE>Uttar Pradesh</STE>
            <CTRY>India</CTRY>
            <PIN>284001</PIN>
          </MA_EMP_AD>
          <MA_EMP_BT>
            <TEL_NO>8726259723</TEL_NO>
          </MA_EMP_BT>
        </MA_EMP>
      </MA>
      <JA>
        <PAN>AUAPD8751B</PAN>
        <FST_NME>SAROJ</FST_NME>
        <LST_NME>DEVI</LST_NME>
        <DOB>1962-01-07</DOB>
        <AGE>61</AGE>
        <GNDR>FEMALE</GNDR>
        <JA_CA>
          <ADD>BIHARIPURA KALI MATA MANDIR K PASS JHANSI </ADD>
          <CTY>Jhansi</CTY>
          <STE>Uttar Pradesh</STE>
          <CTRY>India</CTRY>
          <PIN>284135</PIN>
        </JA_CA>
      </JA>
      <RF>
        <FST_NME>RAVI</FST_NME>
        <RF_MT>
          <TEL_NO>8543890875</TEL_NO>
        </RF_MT>
      </RF>
      <RF>
        <FST_NME>ANIKET</FST_NME>
        <RF_MT>
          <TEL_NO>8543890875</TEL_NO>
        </RF_MT>
      </RF>
    </SUBMISSION>
    <SUBMISSION>
      <APP_VAL>1049868</APP_VAL>
      <TERM>180</TERM>
      <CLASSIFICATION>UNKNOWN</CLASSIFICATION>
      <IDENTIFIER>N_APPL05300166_HOU</IDENTIFIER>
      <PRODUCT>HL_IND</PRODUCT>
      <DATE>2023-11-17</DATE>
      <APP_DTE>2023-11-17</APP_DTE>
      <BRNCH_RGN>UP - Lucknow</BRNCH_RGN>
      <MA>
        <PAN>AFRPU2774B</PAN>
        <FST_NME>SYED</FST_NME>
        <MID_NME>SAMI</MID_NME>
        <LST_NME>ULLAH</LST_NME>
        <DOB>1971-11-24</DOB>
        <AGE>51</AGE>
        <GNDR>MALE</GNDR>
        <MA_CA>
          <ADD>C O SYED GHAZANFAR ULLAH,D 532,KARELIGT B NAGAR,PRAYAGRAJ</ADD>
          <CTY>Allahabad</CTY>
          <STE>Uttar Pradesh</STE>
          <CTRY>India</CTRY>
          <PIN>211016</PIN>
        </MA_CA>
        <MA_PMA>
          <ADD>C O SYED GHAZANFAR ULLAH,D532,KARELIGT B NAGAR,PRAYAGRAJ</ADD>
          <CTY>Allahabad</CTY>
          <STE>Uttar Pradesh</STE>
          <CTRY>India</CTRY>
          <PIN>211016</PIN>
        </MA_PMA>
        <MA_MT>
          <TEL_NO>7905934127</TEL_NO>
        </MA_MT>
        <MA_BNK>
          <BNK_NM>STATE BANK OF INDIA</BNK_NM>
          <ACC_NO>10030138020</ACC_NO>
        </MA_BNK>
        <MA_EMP>
          <ORG_NME>MIZAN TRADERS</ORG_NME>
          <EMP_IND>OTHER</EMP_IND>
          <MA_EMP_AD>
            <ADD>KRELI </ADD>
            <CTY>Allahabad</CTY>
            <STE>Uttar Pradesh</STE>
            <CTRY>India</CTRY>
            <PIN>211016</PIN>
          </MA_EMP_AD>
          <MA_EMP_BT>
            <TEL_NO>7905934127</TEL_NO>
          </MA_EMP_BT>
        </MA_EMP>
      </MA>
      <JA>
        <PAN>DTLPB8626L</PAN>
        <FST_NME>SHABNAM</FST_NME>
        <LST_NME>BEGUM</LST_NME>
        <DOB>1985-11-10</DOB>
        <AGE>37</AGE>
        <GNDR>FEMALE</GNDR>
        <JA_CA>
          <ADD>C O SYED SAMI ULLAH,D532,GTB NAGAR KARELIPRAYAGRAJ</ADD>
          <CTY>Allahabad</CTY>
          <STE>Uttar Pradesh</STE>
          <CTRY>India</CTRY>
          <PIN>211016</PIN>
        </JA_CA>
      </JA>
      <RF>
        <FST_NME>KASHAN</FST_NME>
        <LST_NME>AHMAD</LST_NME>
        <RF_MT>
          <TEL_NO>7007903133</TEL_NO>
        </RF_MT>
      </RF>
      <RF>
        <FST_NME>HAFIZ</FST_NME>
        <LST_NME>ULLAH</LST_NME>
        <RF_MT>
          <TEL_NO>7007903133</TEL_NO>
        </RF_MT>
      </RF>
    </SUBMISSION>
    <SUBMISSION>
      <APP_VAL>850000</APP_VAL>
      <TERM>240</TERM>
      <CLASSIFICATION>UNKNOWN</CLASSIFICATION>
      <IDENTIFIER>W_APPL05300489_HOU</IDENTIFIER>
      <PRODUCT>HL_IND</PRODUCT>
      <DATE>2023-11-17</DATE>
      <APP_DTE>2023-11-17</APP_DTE>
      <BRNCH_RGN>Gujarat</BRNCH_RGN>
      <MA>
        <PAN>DHOPP2695L</PAN>
        <FST_NME>PITHAVA</FST_NME>
        <MID_NME>DIPAKBHAI</MID_NME>
        <LST_NME>DINESHBHAI</LST_NME>
        <DOB>1987-01-01</DOB>
        <AGE>36</AGE>
        <GNDR>MALE</GNDR>
        <MA_CA>
          <ADD>AMARNAGAR ROAD MAHIR 3 APARTMENT BLOCK NO 308</ADD>
          <CTY>Jetpur</CTY>
          <STE>Gujarat</STE>
          <CTRY>India</CTRY>
          <PIN>360370</PIN>
        </MA_CA>
        <MA_PMA>
          <ADD>AMARNAGAR ROAD MAHIR 3 APARTMENT BLOCK NO 308</ADD>
          <CTY>Jetpur</CTY>
          <STE>Gujarat</STE>
          <CTRY>India</CTRY>
          <PIN>360370</PIN>
        </MA_PMA>
        <MA_PROP>
          <ADD>junagadhjunagadh</ADD>
          <CTY>Junagadh</CTY>
          <STE>Gujarat</STE>
          <CTRY>India</CTRY>
          <PIN>362020</PIN>
        </MA_PROP>
        <MA_MT>
          <TEL_NO>9106833474</TEL_NO>
        </MA_MT>
        <MA_BNK>
          <BNK_NM>BANK OF INDIA</BNK_NM>
          <ACC_NO>312410110006551</ACC_NO>
        </MA_BNK>
      </MA>
      <JA>
        <FST_NME>PITHAVA</FST_NME>
        <MID_NME>JIGNASABEN</MID_NME>
        <LST_NME>DIPAKBHAI</LST_NME>
        <DOB>1991-01-01</DOB>
        <AGE>32</AGE>
        <GNDR>FEMALE</GNDR>
        <JA_CA>
          <ADD>AMARNAGAR ROAD MAHIR 3 APARTMENT BLOCK NO 308</ADD>
          <CTY>Jetpur</CTY>
          <STE>Gujarat</STE>
          <CTRY>India</CTRY>
          <PIN>360370</PIN>
        </JA_CA>
      </JA>
      <RF>
        <FST_NME>AJAY</FST_NME>
        <LST_NME>BHAI</LST_NME>
        <RF_MT>
          <TEL_NO>9925932536</TEL_NO>
        </RF_MT>
      </RF>
      <RF>
        <FST_NME>LALA</FST_NME>
        <LST_NME>BHAI</LST_NME>
        <RF_MT>
          <TEL_NO>9925932536</TEL_NO>
        </RF_MT>
      </RF>
    </SUBMISSION>
    <SUBMISSION>
      <APP_VAL>900000</APP_VAL>
      <TERM>120</TERM>
      <CLASSIFICATION>UNKNOWN</CLASSIFICATION>
      <IDENTIFIER>W_APPL05301630_HOU</IDENTIFIER>
      <PRODUCT>HL_IND</PRODUCT>
      <DATE>2023-11-17</DATE>
      <APP_DTE>2023-11-17</APP_DTE>
      <BRNCH_RGN>Gujarat</BRNCH_RGN>
      <MA>
        <PAN>KPYPS7480P</PAN>
        <FST_NME>ISHAK</FST_NME>
        <MID_NME>MUSA</MID_NME>
        <LST_NME>SANDH</LST_NME>
        <DOB>1978-10-15</DOB>
        <AGE>45</AGE>
        <GNDR>MALE</GNDR>
        <MA_CA>
          <ADD>HODIDHAR ROAD</ADD>
          <CTY>Rajkot</CTY>
          <STE>Gujarat</STE>
          <CTRY>India</CTRY>
          <PIN>360450</PIN>
        </MA_CA>
        <MA_PMA>
          <ADD>HODIDHAR ROAD</ADD>
          <CTY>Rajkot</CTY>
          <STE>Gujarat</STE>
          <CTRY>India</CTRY>
          <PIN>360450</PIN>
        </MA_PMA>
        <MA_PROP>
          <ADD>Sheet No.19, C.S.No.2598 &amp; 2600, Nr.Soni Samaj, Braman Street, Off.Main Bazar Road At Bhayavadar-360450, Tal. Upleta &amp; Dist. Rajkot.</ADD>
          <CTY>Rajkot</CTY>
          <STE>Gujarat</STE>
          <CTRY>India</CTRY>
          <PIN>360450</PIN>
        </MA_PROP>
        <MA_MT>
          <TEL_NO>9898532442</TEL_NO>
        </MA_MT>
        <MA_EMP>
          <ORG_NME>ISHAK SANDH</ORG_NME>
          <EMP_IND>TRAVEL</EMP_IND>
          <MA_EMP_AD>
            <ADD>HODIDHAR ROAD</ADD>
            <CTY>Rajkot</CTY>
            <STE>Gujarat</STE>
            <CTRY>India</CTRY>
            <PIN>360450</PIN>
          </MA_EMP_AD>
          <MA_EMP_BT>
            <TEL_NO>9898532442</TEL_NO>
          </MA_EMP_BT>
        </MA_EMP>
      </MA>
      <JA>
        <FST_NME>HASINABEN</FST_NME>
        <MID_NME>YUNUS</MID_NME>
        <LST_NME>SANDH</LST_NME>
        <DOB>1981-01-01</DOB>
        <AGE>42</AGE>
        <GNDR>FEMALE</GNDR>
        <JA_CA>
          <ADD>HODIDHAR VISTAR,AMI</ADD>
          <CTY>Rajkot</CTY>
          <STE>Gujarat</STE>
          <CTRY>India</CTRY>
          <PIN>360450</PIN>
        </JA_CA>
      </JA>
      <BR>
        <ORG_CD>5174</ORG_CD>
        <ORG_NME>Yasin gafarbhai sama</ORG_NME>
        <BR_ADD>
          <ADD>Seven Complex, Bharad Road, Near Ashwani Chowk Opp Ice factory  UP </ADD>
          <CTY>Junagadh</CTY>
          <STE>Gujarat</STE>
          <PIN>362001</PIN>
          <CTRY>INDIA</CTRY>
        </BR_ADD>
      </BR>
      <RF>
        <FST_NME>MUKESHBHAI</FST_NME>
        <RF_MT>
          <TEL_NO>9898176368</TEL_NO>
        </RF_MT>
      </RF>
      <RF>
        <FST_NME>YUNUS</FST_NME>
        <RF_MT>
          <TEL_NO>9898176368</TEL_NO>
        </RF_MT>
      </RF>
    </SUBMISSION>
    <SUBMISSION>
      <APP_VAL>2128655</APP_VAL>
      <TERM>240</TERM>
      <CLASSIFICATION>UNKNOWN</CLASSIFICATION>
      <IDENTIFIER>W_APPL05301566_HOU</IDENTIFIER>
      <PRODUCT>HL_IND</PRODUCT>
      <DATE>2023-11-17</DATE>
      <APP_DTE>2023-11-17</APP_DTE>
      <BRNCH_RGN>Mumbai</BRNCH_RGN>
      <MA>
        <PAN>BBAPM7644G</PAN>
        <FST_NME>MUKESH</FST_NME>
        <MID_NME>SUKUMAR</MID_NME>
        <LST_NME>MALICK</LST_NME>
        <DOB>1991-01-20</DOB>
        <AGE>32</AGE>
        <GNDR>MALE</GNDR>
        <MA_CA>
          <ADD>ROOM NO 004, C WING, SHRIDHAR APT, MUMBRADEVI COLONY,DIVA EAST </ADD>
          <CTY>Thane</CTY>
          <STE>Maharashtra</STE>
          <CTRY>India</CTRY>
          <PIN>400612</PIN>
        </MA_CA>
        <MA_PMA>
          <ADD>ROOM NO 004, C WING, SHRIDHAR APT, MUMBRADEVI COLONY,DIVA EAST </ADD>
          <CTY>Thane</CTY>
          <STE>Maharashtra</STE>
          <CTRY>India</CTRY>
          <PIN>400612</PIN>
        </MA_PMA>
        <MA_MT>
          <TEL_NO>9137486020</TEL_NO>
        </MA_MT>
        <MA_BNK>
          <BNK_NM>HDFC BANK LTD</BNK_NM>
          <ACC_NO>8286</ACC_NO>
        </MA_BNK>
        <MA_EMP>
          <ORG_NME>SARVATRA TECHNOLOGIES PRIVATE LIMITED</ORG_NME>
          <EMP_IND>OTHER</EMP_IND>
          <MA_EMP_AD>
            <ADD>SBI GITC,1 ST FLOOR, SOFTWARE FACTORY DEPARTMENT,CBD BELAPUR </ADD>
            <CTY>Navi Mumbai</CTY>
            <STE>Maharashtra</STE>
            <CTRY>India</CTRY>
            <PIN>400614</PIN>
          </MA_EMP_AD>
          <MA_EMP_BT>
            <TEL_NO>9137486020</TEL_NO>
          </MA_EMP_BT>
        </MA_EMP>
      </MA>
      <JA>
        <PAN>EWJPM7355F</PAN>
        <FST_NME>TUKU</FST_NME>
        <MID_NME>MUKESH</MID_NME>
        <LST_NME>MALICK</LST_NME>
        <DOB>1998-05-12</DOB>
        <AGE>25</AGE>
        <GNDR>FEMALE</GNDR>
        <JA_CA>
          <ADD>ROOM NO 004, C WING, SHRIDHAR APT, MUMBRADEVI COLONY,DIVA EAST </ADD>
          <CTY>Thane</CTY>
          <STE>Maharashtra</STE>
          <CTRY>India</CTRY>
          <PIN>400612</PIN>
        </JA_CA>
      </JA>
      <RF>
        <FST_NME>AKSHAY</FST_NME>
        <LST_NME>BARDE</LST_NME>
        <RF_MT>
          <TEL_NO>9769293949</TEL_NO>
        </RF_MT>
      </RF>
      <RF>
        <FST_NME>RAHUL</FST_NME>
        <LST_NME>PATRE</LST_NME>
        <RF_MT>
          <TEL_NO>9769293949</TEL_NO>
        </RF_MT>
      </RF>
    </SUBMISSION>
    <SUBMISSION>
      <APP_VAL>2205391</APP_VAL>
      <TERM>240</TERM>
      <CLASSIFICATION>UNKNOWN</CLASSIFICATION>
      <IDENTIFIER>W_APPL05300680_HOU</IDENTIFIER>
      <PRODUCT>HL_IND</PRODUCT>
      <DATE>2023-11-17</DATE>
      <APP_DTE>2023-11-17</APP_DTE>
      <BRNCH_RGN>MH - Vidarbha</BRNCH_RGN>
      <MA>
        <PAN>ERFPD8462M</PAN>
        <FST_NME>RASHMI</FST_NME>
        <MID_NME>MANOHAR</MID_NME>
        <LST_NME>DONGARE</LST_NME>
        <DOB>1986-01-07</DOB>
        <AGE>37</AGE>
        <GNDR>FEMALE</GNDR>
        <MA_CA>
          <ADD>PLOT NO 60A BABASAHEB AMBEDKAR SOCIETY MANKAPUR </ADD>
          <CTY>Nagpur</CTY>
          <STE>Maharashtra</STE>
          <CTRY>India</CTRY>
          <PIN>440030</PIN>
        </MA_CA>
        <MA_PMA>
          <ADD>PLOT NO 60A BABASAHEB AMBEDKAR SOCIETY MANKAPUR </ADD>
          <CTY>Nagpur</CTY>
          <STE>Maharashtra</STE>
          <CTRY>India</CTRY>
          <PIN>440030</PIN>
        </MA_PMA>
        <MA_MT>
          <TEL_NO>9763301433</TEL_NO>
        </MA_MT>
        <MA_BNK>
          <BNK_NM>AHMEDNAGAR MERCHANTS CO OP BANK LTD</BNK_NM>
          <ACC_NO>13716</ACC_NO>
        </MA_BNK>
        <MA_EMP>
          <ORG_NME>INDIAN POSTAL</ORG_NME>
          <EMP_IND>OTHER</EMP_IND>
          <MA_EMP_AD>
            <ADD>KAMTEE CITY  AGRWAL BHAWANPOST OFFICE  BAJAR CHOUK </ADD>
            <CTY>Nagpur</CTY>
            <STE>Maharashtra</STE>
            <CTRY>India</CTRY>
            <PIN>441001</PIN>
          </MA_EMP_AD>
          <MA_EMP_BT>
            <TEL_NO>9763301433</TEL_NO>
          </MA_EMP_BT>
        </MA_EMP>
      </MA>
      <JA>
        <PAN>CDEPD4099P</PAN>
        <FST_NME>SUJATA</FST_NME>
        <MID_NME>MANOHAR</MID_NME>
        <LST_NME>DONGARE</LST_NME>
        <DOB>1959-05-11</DOB>
        <AGE>64</AGE>
        <GNDR>FEMALE</GNDR>
        <JA_CA>
          <ADD>PLOT NO 60ABABASAHEB AMBEDKAR SOCIETY </ADD>
          <CTY>Nagpur</CTY>
          <STE>Maharashtra</STE>
          <CTRY>India</CTRY>
          <PIN>440030</PIN>
        </JA_CA>
      </JA>
      <RF>
        <FST_NME>SUBHASH</FST_NME>
        <LST_NME>GAYDHANE</LST_NME>
        <RF_MT>
          <TEL_NO>9822031020</TEL_NO>
        </RF_MT>
      </RF>
      <RF>
        <FST_NME>VIJAY</FST_NME>
        <LST_NME>MISHRA</LST_NME>
        <RF_MT>
          <TEL_NO>9822031020</TEL_NO>
        </RF_MT>
      </RF>
    </SUBMISSION>
    <SUBMISSION>
      <APP_VAL>818030</APP_VAL>
      <TERM>240</TERM>
      <CLASSIFICATION>UNKNOWN</CLASSIFICATION>
      <IDENTIFIER>C_APPL05297999_HOU</IDENTIFIER>
      <PRODUCT>HL_IND</PRODUCT>
      <DATE>2023-11-17</DATE>
      <APP_DTE>2023-11-17</APP_DTE>
      <BRNCH_RGN>UP - Agra</BRNCH_RGN>
      <MA>
        <PAN>GTGPS2675G</PAN>
        <FST_NME>ANAR</FST_NME>
        <LST_NME>SINGH</LST_NME>
        <DOB>1994-01-01</DOB>
        <AGE>29</AGE>
        <GNDR>MALE</GNDR>
        <MA_CA>
          <ADD>S O MURARI LAL,MURALI KA PURA,MURALI KA PURAVISHNORI</ADD>
          <CTY>Morena</CTY>
          <STE>Madhya Pradesh</STE>
          <CTRY>India</CTRY>
          <PIN>476221</PIN>
        </MA_CA>
        <MA_PMA>
          <ADD>S O MURARI LAL,MURALI KA PURA,MURALI KA PURAVISHNORI</ADD>
          <CTY>Morena</CTY>
          <STE>Madhya Pradesh</STE>
          <CTRY>India</CTRY>
          <PIN>476221</PIN>
        </MA_PMA>
        <MA_MT>
          <TEL_NO>7354050735</TEL_NO>
        </MA_MT>
        <MA_BNK>
          <BNK_NM>STATE BANK OF INDIA</BNK_NM>
          <ACC_NO>34234635998</ACC_NO>
        </MA_BNK>
        <MA_EMP>
          <ORG_NME>ANAR SINGH FRUIT COMPANY</ORG_NME>
          <EMP_IND>OTHER</EMP_IND>
          <MA_EMP_AD>
            <ADD>SABJI MANDI</ADD>
            <CTY>Morena</CTY>
            <STE>Madhya Pradesh</STE>
            <CTRY>India</CTRY>
            <PIN>476001</PIN>
          </MA_EMP_AD>
          <MA_EMP_BT>
            <TEL_NO>7354050735</TEL_NO>
          </MA_EMP_BT>
        </MA_EMP>
      </MA>
      <JA>
        <FST_NME>RAMDULARI</FST_NME>
        <LST_NME>RAMDULARI</LST_NME>
        <DOB>1995-01-01</DOB>
        <AGE>28</AGE>
        <GNDR>FEMALE</GNDR>
        <JA_CA>
          <ADD>S O MURARI LAL,MURALI KA PURA,MURALI KA PURAVISHNORI</ADD>
          <CTY>Morena</CTY>
          <STE>Madhya Pradesh</STE>
          <CTRY>India</CTRY>
          <PIN>476221</PIN>
        </JA_CA>
      </JA>
      <BR>
        <ORG_CD>5586</ORG_CD>
        <ORG_NME>IRAM Consultancy</ORG_NME>
      </BR>
      <RF>
        <FST_NME>PANSINGH</FST_NME>
        <RF_MT>
          <TEL_NO>8461929547</TEL_NO>
        </RF_MT>
      </RF>
      <RF>
        <FST_NME>ARUN</FST_NME>
        <RF_MT>
          <TEL_NO>8461929547</TEL_NO>
        </RF_MT>
      </RF>
    </SUBMISSION>
    <SUBMISSION>
      <APP_VAL>352508</APP_VAL>
      <TERM>180</TERM>
      <CLASSIFICATION>UNKNOWN</CLASSIFICATION>
      <IDENTIFIER>W_APPL05300689_NHOU</IDENTIFIER>
      <PRODUCT>NHL_IND</PRODUCT>
      <DATE>2023-11-17</DATE>
      <APP_DTE>2023-11-17</APP_DTE>
      <BRNCH_RGN>MH - Marathwada</BRNCH_RGN>
      <MA>
        <PAN>CFAPK9972C</PAN>
        <FST_NME>SANJAY</FST_NME>
        <MID_NME>NANASAHEB</MID_NME>
        <LST_NME>KOLHE</LST_NME>
        <DOB>1976-06-01</DOB>
        <AGE>47</AGE>
        <GNDR>MALE</GNDR>
        <MA_CA>
          <ADD>LINK ROAD,BHUSHAN,KEDGAON AHMEDNAGAR AHMAD</ADD>
          <CTY>Ahmadnagar</CTY>
          <STE>Maharashtra</STE>
          <CTRY>India</CTRY>
          <PIN>414001</PIN>
        </MA_CA>
        <MA_PMA>
          <ADD>LINK ROAD,BHUSHAN,KEDGAON AHMEDNAGAR AHMAD</ADD>
          <CTY>Ahmadnagar</CTY>
          <STE>Maharashtra</STE>
          <CTRY>India</CTRY>
          <PIN>414001</PIN>
        </MA_PMA>
        <MA_PROP>
          <ADD>NAGAR</ADD>
          <CTY>Ahmadnagar</CTY>
          <STE>Maharashtra</STE>
          <CTRY>India</CTRY>
          <PIN>414005</PIN>
        </MA_PROP>
        <MA_MT>
          <TEL_NO>9307330544</TEL_NO>
        </MA_MT>
        <MA_BNK>
          <BNK_NM>AHMEDNAGAR MERCHANTS CO OP BANK LTD</BNK_NM>
          <ACC_NO>002002100018481</ACC_NO>
        </MA_BNK>
        <MA_EMP>
          <ORG_NME>AJAY GAS AGENCY </ORG_NME>
          <EMP_IND>OTHER</EMP_IND>
          <MA_EMP_AD>
            <ADD>KEDGAON KENTIC CHOWK AHMEDNAGAR </ADD>
            <CTY>Ahmadnagar</CTY>
            <STE>Maharashtra</STE>
            <CTRY>India</CTRY>
            <PIN>414001</PIN>
          </MA_EMP_AD>
          <MA_EMP_BT>
            <TEL_NO>9307330544</TEL_NO>
          </MA_EMP_BT>
        </MA_EMP>
      </MA>
      <JA>
        <FST_NME>ASHA</FST_NME>
        <MID_NME>SANJAY</MID_NME>
        <LST_NME>KOLHE</LST_NME>
        <DOB>1981-05-30</DOB>
        <AGE>42</AGE>
        <GNDR>FEMALE</GNDR>
        <JA_CA>
          <ADD>LINK ROAD,BHUSHAN KEDGAON,AHMEDNAGARAHMADNAGAR </ADD>
          <CTY>Ahmadnagar</CTY>
          <STE>Maharashtra</STE>
          <CTRY>India</CTRY>
          <PIN>414001</PIN>
        </JA_CA>
      </JA>
      <RF>
        <FST_NME>DILIP</FST_NME>
        <LST_NME>PULAVALE</LST_NME>
        <RF_MT>
          <TEL_NO>7020937399</TEL_NO>
        </RF_MT>
      </RF>
      <RF>
        <FST_NME>AJAY</FST_NME>
        <LST_NME>PADALE</LST_NME>
        <RF_MT>
          <TEL_NO>7020937399</TEL_NO>
        </RF_MT>
      </RF>
    </SUBMISSION>
    <SUBMISSION>
      <APP_VAL>414716</APP_VAL>
      <TERM>240</TERM>
      <CLASSIFICATION>UNKNOWN</CLASSIFICATION>
      <IDENTIFIER>W_APPL05300685_HOU</IDENTIFIER>
      <PRODUCT>HL_IND</PRODUCT>
      <DATE>2023-11-17</DATE>
      <APP_DTE>2023-11-17</APP_DTE>
      <BRNCH_RGN>MH - Marathwada</BRNCH_RGN>
      <MA>
        <PAN>CFAPK9972C</PAN>
        <FST_NME>SANJAY</FST_NME>
        <MID_NME>NANASAHEB</MID_NME>
        <LST_NME>KOLHE</LST_NME>
        <DOB>1976-06-01</DOB>
        <AGE>47</AGE>
        <GNDR>MALE</GNDR>
        <MA_CA>
          <ADD>LINK ROAD BHUSHAN KEDGAON,AHMADNAGAR</ADD>
          <CTY>Ahmadnagar</CTY>
          <STE>Maharashtra</STE>
          <CTRY>India</CTRY>
          <PIN>414001</PIN>
        </MA_CA>
        <MA_PMA>
          <ADD>LINK ROAD BHUSHAN KEDGAON,AHMADNAGAR</ADD>
          <CTY>Ahmadnagar</CTY>
          <STE>Maharashtra</STE>
          <CTRY>India</CTRY>
          <PIN>414001</PIN>
        </MA_PMA>
        <MA_PROP>
          <ADD>NAGAR</ADD>
          <CTY>Ahmadnagar</CTY>
          <STE>Maharashtra</STE>
          <CTRY>India</CTRY>
          <PIN>414005</PIN>
        </MA_PROP>
        <MA_MT>
          <TEL_NO>9307330544</TEL_NO>
        </MA_MT>
        <MA_EMP>
          <ORG_NME>AJAY GAS AGENCY </ORG_NME>
          <EMP_IND>OTHER</EMP_IND>
          <MA_EMP_AD>
            <ADD>KEDGAON KENETIK CHOWK AHMEDNAGAR </ADD>
            <CTY>Ahmadnagar</CTY>
            <STE>Maharashtra</STE>
            <CTRY>India</CTRY>
            <PIN>414001</PIN>
          </MA_EMP_AD>
          <MA_EMP_BT>
            <TEL_NO>9307330544</TEL_NO>
          </MA_EMP_BT>
        </MA_EMP>
      </MA>
      <JA>
        <FST_NME>ASHA</FST_NME>
        <MID_NME>SANJAY</MID_NME>
        <LST_NME>KOLHE</LST_NME>
        <DOB>1981-05-30</DOB>
        <AGE>42</AGE>
        <GNDR>FEMALE</GNDR>
        <JA_CA>
          <ADD>LINK ROAD,BHUSHAN,KEDGAON AHMEDNAGAR AHMEDNAGAR,AHMAD</ADD>
          <CTY>Ahmadnagar</CTY>
          <STE>Maharashtra</STE>
          <CTRY>India</CTRY>
          <PIN>414001</PIN>
        </JA_CA>
      </JA>
      <RF>
        <FST_NME>AJAY</FST_NME>
        <LST_NME>PULVALE</LST_NME>
        <RF_MT>
          <TEL_NO>7020937399</TEL_NO>
        </RF_MT>
      </RF>
      <RF>
        <FST_NME>AJAY</FST_NME>
        <LST_NME>PADALE</LST_NME>
        <RF_MT>
          <TEL_NO>7020937399</TEL_NO>
        </RF_MT>
      </RF>
    </SUBMISSION>
    <SUBMISSION>
      <APP_VAL>350283</APP_VAL>
      <TERM>240</TERM>
      <CLASSIFICATION>UNKNOWN</CLASSIFICATION>
      <IDENTIFIER>W_APPL05287448_HOU</IDENTIFIER>
      <PRODUCT>HL_IND</PRODUCT>
      <DATE>2023-11-17</DATE>
      <APP_DTE>2023-09-18</APP_DTE>
      <BRNCH_RGN>MH - Pune</BRNCH_RGN>
      <MA>
        <PAN>CBMPM4332G</PAN>
        <FST_NME>TULSHIDAS</FST_NME>
        <MID_NME>RAGHUNATH</MID_NME>
        <LST_NME>MIRGE</LST_NME>
        <DOB>1986-06-16</DOB>
        <AGE>37</AGE>
        <GNDR>MALE</GNDR>
        <MA_CA>
          <ADD>SR NO-531 2,FLAT NO-29 VIRAJ AVENUE,MULSHI ROADPRADNYA APARTMENT,SADGURU NAGARPIRANGUT</ADD>
          <CTY>Pune</CTY>
          <STE>Maharashtra</STE>
          <CTRY>India</CTRY>
          <PIN>412115</PIN>
        </MA_CA>
        <MA_PMA>
          <ADD>SR NO-531 2,FLAT NO-29 VIRAJ AVENUE,MULSHI ROADPRADNYA APARTMENT,SADGURU NAGARPIRANGUT</ADD>
          <CTY>Pune</CTY>
          <STE>Maharashtra</STE>
          <CTRY>India</CTRY>
          <PIN>412115</PIN>
        </MA_PMA>
        <MA_PROP>
          <ADD>Flat No 29 Fifth floor Viraj Avenue  Milkat No 4867  Old Milkat No 1117 28  Survey No. 531 Hissa No 2 Behind Heera  Garden  Bhugaon Taluka Mulshi District Pune</ADD>
          <CTY>Pune</CTY>
          <STE>Maharashtra</STE>
          <CTRY>India</CTRY>
          <PIN>412115</PIN>
        </MA_PROP>
        <MA_MT>
          <TEL_NO>9657831702</TEL_NO>
        </MA_MT>
        <MA_BNK>
          <BNK_NM>STATE BANK OF INDIA</BNK_NM>
          <ACC_NO>00000020185237417</ACC_NO>
        </MA_BNK>
        <MA_EMP>
          <ORG_NME>PRINCIPLE SECURITY AND ALLIED SERVICES PVT LTD</ORG_NME>
          <EMP_IND>OTHER</EMP_IND>
          <MA_EMP_AD>
            <ADD>IISER PASHAN PUNEPUNE</ADD>
            <CTY>Pune</CTY>
            <STE>Maharashtra</STE>
            <CTRY>India</CTRY>
            <PIN>412115</PIN>
          </MA_EMP_AD>
          <MA_EMP_BT>
            <TEL_NO>9657831702</TEL_NO>
          </MA_EMP_BT>
        </MA_EMP>
      </MA>
      <JA>
        <PAN>BFAPJ1742L</PAN>
        <FST_NME>NIRJALA</FST_NME>
        <MID_NME>VINOD</MID_NME>
        <LST_NME>JOGDAND</LST_NME>
        <DOB>1986-08-01</DOB>
        <AGE>37</AGE>
        <GNDR>FEMALE</GNDR>
        <JA_CA>
          <ADD>SR NO-531 2,FLAT NO-29 VIRAJ AVENUE,MULSHI ROADPRADNYA APARTMENT,SADGURU NAGARPIRANGUT</ADD>
          <CTY>Pune</CTY>
          <STE>Maharashtra</STE>
          <CTRY>India</CTRY>
          <PIN>412115</PIN>
        </JA_CA>
      </JA>
      <RF>
        <FST_NME>BALU</FST_NME>
        <LST_NME>MADNE</LST_NME>
        <RF_MT>
          <TEL_NO>9850725109</TEL_NO>
        </RF_MT>
      </RF>
      <RF>
        <FST_NME>PRAVIN</FST_NME>
        <LST_NME>CHAVAN</LST_NME>
        <RF_MT>
          <TEL_NO>9850725109</TEL_NO>
        </RF_MT>
      </RF>
    </SUBMISSION>
    <SUBMISSION>
      <APP_VAL>443937</APP_VAL>
      <TERM>180</TERM>
      <CLASSIFICATION>UNKNOWN</CLASSIFICATION>
      <IDENTIFIER>W_APPL05300750_NHOU</IDENTIFIER>
      <PRODUCT>NHL_IND</PRODUCT>
      <DATE>2023-11-17</DATE>
      <APP_DTE>2023-11-17</APP_DTE>
      <BRNCH_RGN>MH - Pune</BRNCH_RGN>
      <MA>
        <PAN>IMOPS6522P</PAN>
        <FST_NME>PRASHANT</FST_NME>
        <MID_NME>BAPU</MID_NME>
        <LST_NME>SAPKAL</LST_NME>
        <DOB>1997-07-06</DOB>
        <AGE>26</AGE>
        <GNDR>MALE</GNDR>
        <MA_CA>
          <ADD>GAVATHAN SHIVAJINAGAR TAL KHANDALADIST SATARA</ADD>
          <CTY>Satara</CTY>
          <STE>Maharashtra</STE>
          <CTRY>India</CTRY>
          <PIN>412802</PIN>
        </MA_CA>
        <MA_PMA>
          <ADD>GAVATHAN SHIVAJINAGAR TAL KHANDALADIST SATARA</ADD>
          <CTY>Satara</CTY>
          <STE>Maharashtra</STE>
          <CTRY>India</CTRY>
          <PIN>412802</PIN>
        </MA_PMA>
        <MA_MT>
          <TEL_NO>9561980438</TEL_NO>
        </MA_MT>
        <MA_BNK>
          <BNK_NM>IDFC BANK LIMITED</BNK_NM>
          <ACC_NO>10072632205</ACC_NO>
        </MA_BNK>
        <MA_EMP>
          <ORG_NME>TBK INDIA PVTLTD</ORG_NME>
          <EMP_IND>OTHER</EMP_IND>
          <MA_EMP_AD>
            <ADD>GAT NO 103 264 658 666 TO 719 721 749 7 LONAND ROAD VILLEGE MAHAVASHI TAL KHANDARA DIST SATARA</ADD>
            <CTY>Satara</CTY>
            <STE>Maharashtra</STE>
            <CTRY>India</CTRY>
            <PIN>412802</PIN>
          </MA_EMP_AD>
          <MA_EMP_BT>
            <TEL_NO>9561980438</TEL_NO>
          </MA_EMP_BT>
        </MA_EMP>
      </MA>
      <JA>
        <PAN>BONPS5299R</PAN>
        <FST_NME>BAPU</FST_NME>
        <MID_NME>DAGADU</MID_NME>
        <LST_NME>SAPKAL</LST_NME>
        <DOB>1963-06-01</DOB>
        <AGE>60</AGE>
        <GNDR>MALE</GNDR>
        <JA_CA>
          <ADD>GAVATHAN SHIVAJINAGAR TAL KHANDALADIST SATARA</ADD>
          <CTY>Satara</CTY>
          <STE>Maharashtra</STE>
          <CTRY>India</CTRY>
          <PIN>412802</PIN>
        </JA_CA>
      </JA>
      <RF>
        <FST_NME>PRAJVAL</FST_NME>
        <LST_NME>SAPKAL</LST_NME>
        <RF_MT>
          <TEL_NO>7387754648</TEL_NO>
        </RF_MT>
      </RF>
      <RF>
        <FST_NME>AKSHAY</FST_NME>
        <LST_NME>SAPKAL</LST_NME>
        <RF_MT>
          <TEL_NO>7387754648</TEL_NO>
        </RF_MT>
      </RF>
    </SUBMISSION>
    <SUBMISSION>
      <APP_VAL>1154423</APP_VAL>
      <TERM>240</TERM>
      <CLASSIFICATION>UNKNOWN</CLASSIFICATION>
      <IDENTIFIER>W_APPL05300635_HOU</IDENTIFIER>
      <PRODUCT>HL_IND</PRODUCT>
      <DATE>2023-11-17</DATE>
      <APP_DTE>2023-11-17</APP_DTE>
      <BRNCH_RGN>Rajasthan</BRNCH_RGN>
      <MA>
        <PAN>HYMPK7511M</PAN>
        <FST_NME>TAHIR</FST_NME>
        <LST_NME>KHAN</LST_NME>
        <DOB>1996-02-01</DOB>
        <AGE>27</AGE>
        <GNDR>MALE</GNDR>
        <MA_CA>
          <ADD>AMAGARH SHAKTI COLONYDELHI BY PASSJAIPUR </ADD>
          <CTY>Jaipur</CTY>
          <STE>Rajasthan</STE>
          <CTRY>India</CTRY>
          <PIN>302003</PIN>
        </MA_CA>
        <MA_PMA>
          <ADD>VILL JALALI DIST ALIGARH UTTAR PRADESH </ADD>
          <CTY>Aligarh</CTY>
          <STE>Uttar Pradesh</STE>
          <CTRY>India</CTRY>
          <PIN>202128</PIN>
        </MA_PMA>
        <MA_PROP>
          <ADD> Jaipur </ADD>
          <CTY>Jaipur</CTY>
          <STE>Rajasthan</STE>
          <CTRY>India</CTRY>
          <PIN>302001</PIN>
        </MA_PROP>
        <MA_MT>
          <TEL_NO>9782562382</TEL_NO>
        </MA_MT>
        <MA_EMP>
          <ORG_NME> K A MOTORS </ORG_NME>
          <EMP_IND>OTHER</EMP_IND>
          <MA_EMP_AD>
            <ADD>SHOP NO CC 279 GOL MARKET JAWAHAR NAGAR JAIPUR </ADD>
            <CTY>Jaipur</CTY>
            <STE>Rajasthan</STE>
            <CTRY>India</CTRY>
            <PIN>302002</PIN>
          </MA_EMP_AD>
          <MA_EMP_BT>
            <TEL_NO>9782562382</TEL_NO>
          </MA_EMP_BT>
        </MA_EMP>
      </MA>
      <JA>
        <FST_NME>GULJAHAN</FST_NME>
        <LST_NME>GULJAHAN</LST_NME>
        <DOB>1976-01-01</DOB>
        <AGE>47</AGE>
        <GNDR>FEMALE</GNDR>
        <JA_CA>
          <ADD>AMAGARH SHAKTI COLONYDELHI BY PASSJAIPUR </ADD>
          <CTY>Jaipur</CTY>
          <STE>Rajasthan</STE>
          <CTRY>India</CTRY>
          <PIN>302003</PIN>
        </JA_CA>
      </JA>
      <BR>
        <ORG_CD>5670</ORG_CD>
        <ORG_NME>Waheguru Associates</ORG_NME>
      </BR>
      <RF>
        <FST_NME>JAHID</FST_NME>
        <LST_NME>KHAN</LST_NME>
        <RF_MT>
          <TEL_NO>9828267875</TEL_NO>
        </RF_MT>
      </RF>
      <RF>
        <FST_NME>SOKAT</FST_NME>
        <LST_NME>ALI</LST_NME>
        <RF_MT>
          <TEL_NO>9828267875</TEL_NO>
        </RF_MT>
      </RF>
    </SUBMISSION>
    <SUBMISSION>
      <APP_VAL>1071990</APP_VAL>
      <TERM>240</TERM>
      <CLASSIFICATION>UNKNOWN</CLASSIFICATION>
      <IDENTIFIER>N_APPL05299891_HOU</IDENTIFIER>
      <PRODUCT>HL_IND</PRODUCT>
      <DATE>2023-11-17</DATE>
      <APP_DTE>2023-11-17</APP_DTE>
      <BRNCH_RGN>Burari</BRNCH_RGN>
      <MA>
        <PAN>COQPM1979C</PAN>
        <FST_NME>BRIJ</FST_NME>
        <LST_NME>MOHAN</LST_NME>
        <DOB>1981-05-04</DOB>
        <AGE>42</AGE>
        <GNDR>MALE</GNDR>
        <MA_CA>
          <ADD>HOUSE NO 16 GALI NO1 JARODA PART 3BURARI</ADD>
          <CTY>North Delhi</CTY>
          <STE>Delhi</STE>
          <CTRY>India</CTRY>
          <PIN>110084</PIN>
        </MA_CA>
        <MA_PMA>
          <ADD>HOUSE NO 16 GALI NO1 JARODA PART 3BURARI</ADD>
          <CTY>North Delhi</CTY>
          <STE>Delhi</STE>
          <CTRY>India</CTRY>
          <PIN>110084</PIN>
        </MA_PMA>
        <MA_PROP>
          <ADD>HOUSE NO 16 JARODA PART 3BURARI</ADD>
          <CTY>North Delhi</CTY>
          <STE>Delhi</STE>
          <CTRY>India</CTRY>
          <PIN>110084</PIN>
        </MA_PROP>
        <MA_MT>
          <TEL_NO>9811865828</TEL_NO>
        </MA_MT>
        <MA_BNK>
          <BNK_NM>STATE BANK OF INDIA</BNK_NM>
          <ACC_NO>10442031099</ACC_NO>
        </MA_BNK>
        <MA_EMP>
          <ORG_NME>brij mohan</ORG_NME>
          <EMP_IND>OTHER</EMP_IND>
          <MA_EMP_AD>
            <ADD>HOUSE NO 16 JARODA PART 3BURARI</ADD>
            <CTY>North Delhi</CTY>
            <STE>Delhi</STE>
            <CTRY>India</CTRY>
            <PIN>110084</PIN>
          </MA_EMP_AD>
          <MA_EMP_BT>
            <TEL_NO>9811865828</TEL_NO>
          </MA_EMP_BT>
        </MA_EMP>
      </MA>
      <JA>
        <PAN>CGAPG6634E</PAN>
        <FST_NME>GEETA</FST_NME>
        <LST_NME>GEETA</LST_NME>
        <DOB>1984-01-01</DOB>
        <AGE>39</AGE>
        <GNDR>FEMALE</GNDR>
        <JA_CA>
          <ADD>HOUSE NO 16 GALI NO1 JARODA PART 3BURARI</ADD>
          <CTY>North Delhi</CTY>
          <STE>Delhi</STE>
          <CTRY>India</CTRY>
          <PIN>110084</PIN>
        </JA_CA>
      </JA>
      <BR>
        <ORG_CD>4477</ORG_CD>
        <ORG_NME>Easy Loans</ORG_NME>
        <BR_ADD>
          <ADD>A   7  4th Floor  Sector   10 A   7  4th Floor  Sector   10</ADD>
          <CTY>East Delhi</CTY>
          <STE>Delhi</STE>
          <PIN>110092</PIN>
          <CTRY>INDIA</CTRY>
        </BR_ADD>
      </BR>
      <RF>
        <FST_NME>RAJKUMAR</FST_NME>
        <RF_MT>
          <TEL_NO>9818893469</TEL_NO>
        </RF_MT>
      </RF>
      <RF>
        <FST_NME>DEEPAK</FST_NME>
        <RF_MT>
          <TEL_NO>9818893469</TEL_NO>
        </RF_MT>
      </RF>
    </SUBMISSION>
    <SUBMISSION>
      <APP_VAL>719986</APP_VAL>
      <TERM>240</TERM>
      <CLASSIFICATION>UNKNOWN</CLASSIFICATION>
      <IDENTIFIER>N_APPL05300759_HOU</IDENTIFIER>
      <PRODUCT>HL_IND</PRODUCT>
      <DATE>2023-11-17</DATE>
      <APP_DTE>2023-11-17</APP_DTE>
      <BRNCH_RGN>Burari</BRNCH_RGN>
      <MA>
        <PAN>AQHPY7334G</PAN>
        <FST_NME>MUKESH</FST_NME>
        <LST_NME>YADAV</LST_NME>
        <DOB>1979-04-07</DOB>
        <AGE>44</AGE>
        <GNDR>MALE</GNDR>
        <MA_CA>
          <ADD>S O SAUDAGAR,HOUSE NO C-305,C-BLOCKNEW SEEMAPURI NEW SEEMAPURI,EAST</ADD>
          <CTY>East Delhi</CTY>
          <STE>Delhi</STE>
          <CTRY>India</CTRY>
          <PIN>110095</PIN>
        </MA_CA>
        <MA_PMA>
          <ADD>S O SAUDAGAR,HOUSE NO C-305,C-BLOCKNEW SEEMAPURI NEW SEEMAPURI,EAST</ADD>
          <CTY>East Delhi</CTY>
          <STE>Delhi</STE>
          <CTRY>India</CTRY>
          <PIN>110095</PIN>
        </MA_PMA>
        <MA_PROP>
          <ADD>C-306, NEW SEEMAPURI EST DELHI</ADD>
          <CTY>East Delhi</CTY>
          <STE>Delhi</STE>
          <CTRY>India</CTRY>
          <PIN>110095</PIN>
        </MA_PROP>
        <MA_MT>
          <TEL_NO>9643590711</TEL_NO>
        </MA_MT>
        <MA_BNK>
          <BNK_NM>PUNJAB NATIONAL BANK</BNK_NM>
          <ACC_NO>92001700001616</ACC_NO>
        </MA_BNK>
        <MA_EMP>
          <ORG_NME>mukeash yadav</ORG_NME>
          <EMP_IND>TRAVEL</EMP_IND>
          <MA_EMP_AD>
            <ADD>C-306, NEW SEEMAPURI EST DELHI</ADD>
            <CTY>East Delhi</CTY>
            <STE>Delhi</STE>
            <CTRY>India</CTRY>
            <PIN>110095</PIN>
          </MA_EMP_AD>
          <MA_EMP_BT>
            <TEL_NO>9643590711</TEL_NO>
          </MA_EMP_BT>
        </MA_EMP>
      </MA>
      <JA>
        <FST_NME>LALITA</FST_NME>
        <LST_NME>DEVI</LST_NME>
        <DOB>1988-01-01</DOB>
        <AGE>35</AGE>
        <GNDR>FEMALE</GNDR>
        <JA_CA>
          <ADD>,HOUSE NO.C-305,C-BLOCKNEW SEEMAPURI NEW SEEMAPURI,EAST</ADD>
          <CTY>East Delhi</CTY>
          <STE>Delhi</STE>
          <CTRY>India</CTRY>
          <PIN>110095</PIN>
        </JA_CA>
      </JA>
      <RF>
        <FST_NME>MADHUSUDAN</FST_NME>
        <LST_NME>YADAV</LST_NME>
        <RF_MT>
          <TEL_NO>8797356097</TEL_NO>
        </RF_MT>
      </RF>
      <RF>
        <FST_NME>UDAY</FST_NME>
        <LST_NME>YADAV</LST_NME>
        <RF_MT>
          <TEL_NO>8797356097</TEL_NO>
        </RF_MT>
      </RF>
    </SUBMISSION>
    <SUBMISSION>
      <APP_VAL>1273374</APP_VAL>
      <TERM>240</TERM>
      <CLASSIFICATION>UNKNOWN</CLASSIFICATION>
      <IDENTIFIER>W_APPL05301334_HOU</IDENTIFIER>
      <PRODUCT>HL_IND</PRODUCT>
      <DATE>2023-11-17</DATE>
      <APP_DTE>2023-11-17</APP_DTE>
      <BRNCH_RGN>Naigaon</BRNCH_RGN>
      <MA>
        <PAN>AKKPD7909F</PAN>
        <FST_NME>MONTO</FST_NME>
        <MID_NME>PRAKASHCHAND</MID_NME>
        <LST_NME>DEVNATH</LST_NME>
        <DOB>1979-10-10</DOB>
        <AGE>44</AGE>
        <GNDR>MALE</GNDR>
        <MA_CA>
          <ADD>ROOM NO 8,AMRUT NAGAR MB ESTATE,VIRAR WEST</ADD>
          <CTY>Navi Mumbai</CTY>
          <STE>Maharashtra</STE>
          <CTRY>India</CTRY>
          <PIN>401303</PIN>
        </MA_CA>
        <MA_PMA>
          <ADD>ROOM NO 8,AMRUT NAGAR MB ESTATE,VIRAR WEST</ADD>
          <CTY>Navi Mumbai</CTY>
          <STE>Maharashtra</STE>
          <CTRY>India</CTRY>
          <PIN>401303</PIN>
        </MA_PMA>
        <MA_MT>
          <TEL_NO>9819811935</TEL_NO>
        </MA_MT>
        <MA_EMA>
          <EMA_ADD>MONTO.DEVNATH1979@GMAIL.COM</EMA_ADD>
        </MA_EMA>
        <MA_BNK>
          <BNK_NM>HDFC BANK</BNK_NM>
          <ACC_NO>50100016554900</ACC_NO>
        </MA_BNK>
        <MA_EMP>
          <ORG_NME>SLIMLITE ELECTRICAL PVT LTD</ORG_NME>
          <EMP_IND>MANAFACTURING</EMP_IND>
          <MA_EMP_AD>
            <ADD>DHIRAJ HERITAGE COMMERCIAL GALA 212,SV ROAD SANTACRUZ WEST </ADD>
            <CTY>Mumbai</CTY>
            <STE>Maharashtra</STE>
            <CTRY>India</CTRY>
            <PIN>400054</PIN>
          </MA_EMP_AD>
          <MA_EMP_BT>
            <TEL_NO>9819811935</TEL_NO>
          </MA_EMP_BT>
        </MA_EMP>
      </MA>
      <JA>
        <PAN>BLVPD3860Q</PAN>
        <FST_NME>SUNITA</FST_NME>
        <MID_NME>MONTO</MID_NME>
        <LST_NME>DEVNATH</LST_NME>
        <DOB>1981-06-07</DOB>
        <AGE>42</AGE>
        <GNDR>FEMALE</GNDR>
        <JA_CA>
          <ADD>ROOM NO 8,AMRUT NAGAR MB ESTATE,VIRAR WEST</ADD>
          <CTY>Navi Mumbai</CTY>
          <STE>Maharashtra</STE>
          <CTRY>India</CTRY>
          <PIN>401303</PIN>
        </JA_CA>
      </JA>
      <RF>
        <FST_NME>SANJAY</FST_NME>
        <RF_MT>
          <TEL_NO>9820582580</TEL_NO>
        </RF_MT>
      </RF>
      <RF>
        <FST_NME>OMPRAKASH</FST_NME>
        <RF_MT>
          <TEL_NO>9820582580</TEL_NO>
        </RF_MT>
      </RF>
    </SUBMISSION>
    <SUBMISSION>
      <APP_VAL>1930326</APP_VAL>
      <TERM>108</TERM>
      <CLASSIFICATION>UNKNOWN</CLASSIFICATION>
      <IDENTIFIER>N_APPL05300717_HOU</IDENTIFIER>
      <PRODUCT>HL_IND</PRODUCT>
      <DATE>2023-11-17</DATE>
      <APP_DTE>2023-11-17</APP_DTE>
      <BRNCH_RGN>Mohali</BRNCH_RGN>
      <MA>
        <PAN>CBDPS6546M</PAN>
        <FST_NME>HARPREET</FST_NME>
        <LST_NME>SINGH</LST_NME>
        <DOB>1985-10-21</DOB>
        <AGE>38</AGE>
        <GNDR>MALE</GNDR>
        <MA_CA>
          <ADD>S O RAJMAL SINGH,HOUSE NO.119,NEAR CIVIL HOSPITALWARD NO.6,KURALI,SAS NAGAR MOHALI</ADD>
          <CTY>Kurali</CTY>
          <STE>Punjab</STE>
          <CTRY>India</CTRY>
          <PIN>140103</PIN>
        </MA_CA>
        <MA_PMA>
          <ADD>S O RAJMAL SINGH,HOUSE NO.119,NEAR CIVIL HOSPITALWARD NO.6,KURALI,SAS NAGAR MOHALI</ADD>
          <CTY>Kurali</CTY>
          <STE>Punjab</STE>
          <CTRY>India</CTRY>
          <PIN>140103</PIN>
        </MA_PMA>
        <MA_MT>
          <TEL_NO>9855679006</TEL_NO>
        </MA_MT>
        <MA_BNK>
          <BNK_NM>STATE BANK OF INDIA</BNK_NM>
          <ACC_NO>00000039905084770</ACC_NO>
        </MA_BNK>
        <MA_EMP>
          <ORG_NME>INNOVISION LIMITED  CIVIL HOSPITAL PHASE 6</ORG_NME>
          <EMP_IND>OTHER</EMP_IND>
          <MA_EMP_AD>
            <ADD>SITTING IN CIVIL HOSPITAL PHASE 6GENRAL OT ROOM NO 101</ADD>
            <CTY>Mohali</CTY>
            <STE>Punjab</STE>
            <CTRY>India</CTRY>
            <PIN>140110</PIN>
          </MA_EMP_AD>
          <MA_EMP_BT>
            <TEL_NO>9855679006</TEL_NO>
          </MA_EMP_BT>
        </MA_EMP>
      </MA>
      <JA>
        <PAN>AFFPK4061F</PAN>
        <FST_NME>BALWINDER</FST_NME>
        <LST_NME>KAUR</LST_NME>
        <DOB>1963-06-05</DOB>
        <AGE>60</AGE>
        <GNDR>FEMALE</GNDR>
        <JA_CA>
          <ADD>HOUSE NO 119 WARD NO 6 SAS NAGARMOHALI KURALI</ADD>
          <CTY>Kurali</CTY>
          <STE>Punjab</STE>
          <CTRY>India</CTRY>
          <PIN>140103</PIN>
        </JA_CA>
      </JA>
      <RF>
        <FST_NME>GURPAL</FST_NME>
        <LST_NME>SINGH</LST_NME>
        <RF_MT>
          <TEL_NO>9878847243</TEL_NO>
        </RF_MT>
      </RF>
      <RF>
        <FST_NME>PREET</FST_NME>
        <LST_NME>BHARGHAV</LST_NME>
        <RF_MT>
          <TEL_NO>9878847243</TEL_NO>
        </RF_MT>
      </RF>
    </SUBMISSION>
    <SUBMISSION>
      <APP_VAL>1049476</APP_VAL>
      <TERM>240</TERM>
      <CLASSIFICATION>UNKNOWN</CLASSIFICATION>
      <IDENTIFIER>N_APPL05300478_HOU</IDENTIFIER>
      <PRODUCT>HL_IND</PRODUCT>
      <DATE>2023-11-17</DATE>
      <APP_DTE>2023-11-17</APP_DTE>
      <BRNCH_RGN>Delhi-Mayur Vihar</BRNCH_RGN>
      <MA>
        <PAN>EHQPK3498R</PAN>
        <FST_NME>VINOD</FST_NME>
        <MID_NME>KUMAR</MID_NME>
        <LST_NME>KANDPAL</LST_NME>
        <DOB>1996-07-16</DOB>
        <AGE>27</AGE>
        <GNDR>MALE</GNDR>
        <MA_CA>
          <ADD>S O KANTA BALLABH KANDPAL,RC 332,BHARAT NAGAR COLONY</ADD>
          <CTY>Ghaziabad</CTY>
          <STE>Uttar Pradesh</STE>
          <CTRY>India</CTRY>
          <PIN>201309</PIN>
        </MA_CA>
        <MA_PMA>
          <ADD>S O KANTA BALLABH KANDPAL,RC 332,BHARAT NAGAR COLONY</ADD>
          <CTY>Ghaziabad</CTY>
          <STE>Uttar Pradesh</STE>
          <CTRY>India</CTRY>
          <PIN>201309</PIN>
        </MA_PMA>
        <MA_MT>
          <TEL_NO>8929426289</TEL_NO>
        </MA_MT>
        <MA_BNK>
          <BNK_NM>KOTAK MAHINDRA BANK LIMITED</BNK_NM>
          <ACC_NO>5945788617</ACC_NO>
        </MA_BNK>
      </MA>
      <JA>
        <PAN>JFMPD0473N</PAN>
        <FST_NME>PREMA</FST_NME>
        <LST_NME>DEVI</LST_NME>
        <DOB>1975-01-01</DOB>
        <AGE>48</AGE>
        <GNDR>FEMALE</GNDR>
        <JA_CA>
          <ADD>S O KANTA BALLABH KANDPAL,RC 332,BHARAT NAGAR COLONY</ADD>
          <CTY>Ghaziabad</CTY>
          <STE>Uttar Pradesh</STE>
          <CTRY>India</CTRY>
          <PIN>201309</PIN>
        </JA_CA>
      </JA>
      <RF>
        <FST_NME>VIKAS</FST_NME>
        <RF_MT>
          <TEL_NO>9560723597</TEL_NO>
        </RF_MT>
      </RF>
      <RF>
        <FST_NME>JAGDISH</FST_NME>
        <RF_MT>
          <TEL_NO>9560723597</TEL_NO>
        </RF_MT>
      </RF>
    </SUBMISSION>
    <SUBMISSION>
      <APP_VAL>1964824</APP_VAL>
      <TERM>240</TERM>
      <CLASSIFICATION>UNKNOWN</CLASSIFICATION>
      <IDENTIFIER>W_APPL05298832_HOU</IDENTIFIER>
      <PRODUCT>HL_IND</PRODUCT>
      <DATE>2023-11-17</DATE>
      <APP_DTE>2023-11-17</APP_DTE>
      <BRNCH_RGN>Nagpur-Nelson Square</BRNCH_RGN>
      <MA>
        <PAN>GJTPS1973J</PAN>
        <FST_NME>SAPANA</FST_NME>
        <MID_NME>RITESH</MID_NME>
        <LST_NME>SAHARE</LST_NME>
        <DOB>1987-07-31</DOB>
        <AGE>36</AGE>
        <GNDR>FEMALE</GNDR>
        <MA_CA>
          <ADD>PLOT NO.62,NARI LAYOUT,NEAR BUDDHA VIHARKABIR NAGAR,UPPALWADI</ADD>
          <CTY>Nagpur</CTY>
          <STE>Maharashtra</STE>
          <CTRY>India</CTRY>
          <PIN>440026</PIN>
        </MA_CA>
        <MA_PMA>
          <ADD>PLOT NO.62,NARI LAYOUT,NEAR BUDDHA VIHARKABIR NAGAR,UPPALWADI</ADD>
          <CTY>Nagpur</CTY>
          <STE>Maharashtra</STE>
          <CTRY>India</CTRY>
          <PIN>440026</PIN>
        </MA_PMA>
        <MA_MT>
          <TEL_NO>8421108003</TEL_NO>
        </MA_MT>
        <MA_BNK>
          <BNK_NM>UNION BANK OF INDIA</BNK_NM>
          <ACC_NO>442402010922293</ACC_NO>
        </MA_BNK>
        <MA_EMP>
          <ORG_NME>CJSD</ORG_NME>
          <EMP_IND>OTHER</EMP_IND>
          <MA_EMP_AD>
            <ADD> CIVIL JAUGE JUNIOR DIVISIONNEAR BHRAMNI FATA KALMESHWAR</ADD>
            <CTY>Nagpur</CTY>
            <STE>Maharashtra</STE>
            <CTRY>India</CTRY>
            <PIN>441501</PIN>
          </MA_EMP_AD>
          <MA_EMP_BT>
            <TEL_NO>8421108003</TEL_NO>
          </MA_EMP_BT>
        </MA_EMP>
      </MA>
      <JA>
        <PAN>BJZPS4175D</PAN>
        <FST_NME>RITESH</FST_NME>
        <MID_NME>CHANDRSHEKHER</MID_NME>
        <LST_NME>SAHARE</LST_NME>
        <DOB>1982-04-20</DOB>
        <AGE>41</AGE>
        <GNDR>MALE</GNDR>
        <JA_CA>
          <ADD>S O CHANDRSHEKHER ASARAM SAHARE,NEAR KABIR NAGAR BUDDHA VIHAR,PLOT NO62 KABIR NAGAR NARI LAY OUTUPPALWADI S.O</ADD>
          <CTY>Nagpur</CTY>
          <STE>Maharashtra</STE>
          <CTRY>India</CTRY>
          <PIN>440026</PIN>
        </JA_CA>
      </JA>
      <RF>
        <FST_NME>NILESH</FST_NME>
        <LST_NME>SAHARE</LST_NME>
        <RF_MT>
          <TEL_NO>9373229745</TEL_NO>
        </RF_MT>
      </RF>
      <RF>
        <FST_NME>SHAILEAH</FST_NME>
        <LST_NME>SHENDE</LST_NME>
        <RF_MT>
          <TEL_NO>9373229745</TEL_NO>
        </RF_MT>
      </RF>
    </SUBMISSION>
    <SUBMISSION>
      <APP_VAL>1600130</APP_VAL>
      <TERM>180</TERM>
      <CLASSIFICATION>UNKNOWN</CLASSIFICATION>
      <IDENTIFIER>W_APPL05300351_NHOU</IDENTIFIER>
      <PRODUCT>NHL_IND</PRODUCT>
      <DATE>2023-11-17</DATE>
      <APP_DTE>2023-11-17</APP_DTE>
      <BRNCH_RGN>Nagpur-Nelson Square</BRNCH_RGN>
      <MA>
        <PAN>DGSPB9636L</PAN>
        <FST_NME>AKSHAY</FST_NME>
        <MID_NME>GANESH</MID_NME>
        <LST_NME>BANDHEKAR</LST_NME>
        <DOB>1993-07-21</DOB>
        <AGE>30</AGE>
        <GNDR>MALE</GNDR>
        <MA_CA>
          <ADD>CO SHANKARRAO SHENDREPLOT NO 21 ANMOL NAGARWATHODA RING ROAD </ADD>
          <CTY>Nagpur</CTY>
          <STE>Maharashtra</STE>
          <CTRY>India</CTRY>
          <PIN>440008</PIN>
        </MA_CA>
        <MA_PMA>
          <ADD>CO SHANKARRAO SHENDREPLOT NO 21 ANMOL NAGARWATHODA RING ROAD </ADD>
          <CTY>Nagpur</CTY>
          <STE>Maharashtra</STE>
          <CTRY>India</CTRY>
          <PIN>440008</PIN>
        </MA_PMA>
        <MA_MT>
          <TEL_NO>9665696623</TEL_NO>
        </MA_MT>
        <MA_EMA>
          <EMA_ADD>BANDHEKAR.AKSHAY@GMAIL.COM</EMA_ADD>
        </MA_EMA>
        <MA_BNK>
          <BNK_NM>UCO BANK</BNK_NM>
          <ACC_NO>19280110006337</ACC_NO>
        </MA_BNK>
      </MA>
      <JA>
        <PAN>AXJPB5965B</PAN>
        <FST_NME>KAVITA</FST_NME>
        <MID_NME>GANESH</MID_NME>
        <LST_NME>BANDHEKAR</LST_NME>
        <DOB>1970-11-16</DOB>
        <AGE>53</AGE>
        <GNDR>FEMALE</GNDR>
        <JA_CA>
          <ADD>CO SHANKARRAO SHENDREPLOT NO 21 ANMOL NAGARWATHODA RING ROAD </ADD>
          <CTY>Nagpur</CTY>
          <STE>Maharashtra</STE>
          <CTRY>India</CTRY>
          <PIN>440008</PIN>
        </JA_CA>
      </JA>
      <RF>
        <FST_NME>GULSHAN</FST_NME>
        <LST_NME>RAMCHANDANI</LST_NME>
        <RF_MT>
          <TEL_NO>9145747955</TEL_NO>
        </RF_MT>
      </RF>
      <RF>
        <FST_NME>ANKIT</FST_NME>
        <LST_NME>KALE</LST_NME>
        <RF_MT>
          <TEL_NO>9145747955</TEL_NO>
        </RF_MT>
      </RF>
    </SUBMISSION>
    <SUBMISSION>
      <APP_VAL>1105109</APP_VAL>
      <TERM>240</TERM>
      <CLASSIFICATION>UNKNOWN</CLASSIFICATION>
      <IDENTIFIER>W_APPL05300223_HOU</IDENTIFIER>
      <PRODUCT>HL_IND</PRODUCT>
      <DATE>2023-11-17</DATE>
      <APP_DTE>2023-11-17</APP_DTE>
      <BRNCH_RGN>JALNA</BRNCH_RGN>
      <MA>
        <PAN>BSBPN4812R</PAN>
        <FST_NME>SANTOSH</FST_NME>
        <MID_NME>RAMCHANDRAJI</MID_NME>
        <LST_NME>NAVANDAR</LST_NME>
        <DOB>1972-04-07</DOB>
        <AGE>51</AGE>
        <GNDR>MALE</GNDR>
        <MA_CA>
          <ADD>PRIYADARSHNI COLONY,SAMBHAJI NAGAR,JALNA</ADD>
          <CTY>Jalna</CTY>
          <STE>Maharashtra</STE>
          <CTRY>India</CTRY>
          <PIN>431203</PIN>
        </MA_CA>
        <MA_PMA>
          <ADD>PRIYADARSHNI COLONY,SAMBHAJI NAGAR,JALNA</ADD>
          <CTY>Jalna</CTY>
          <STE>Maharashtra</STE>
          <CTRY>India</CTRY>
          <PIN>431203</PIN>
        </MA_PMA>
        <MA_MT>
          <TEL_NO>9960125633</TEL_NO>
        </MA_MT>
        <MA_EMA>
          <EMA_ADD>NAVANDARSANTOSH1@GMAIL.COM</EMA_ADD>
        </MA_EMA>
        <MA_BNK>
          <BNK_NM>UNION BANK OF INDIA</BNK_NM>
          <ACC_NO>323002010084043</ACC_NO>
        </MA_BNK>
        <MA_EMP>
          <ORG_NME>Kanahya Kirana</ORG_NME>
          <EMP_IND>OTHER</EMP_IND>
          <MA_EMP_AD>
            <ADD>KANAHAYA KIRANAMIDC JALNAJALNA</ADD>
            <CTY>Jalna</CTY>
            <STE>Maharashtra</STE>
            <CTRY>India</CTRY>
            <PIN>431203</PIN>
          </MA_EMP_AD>
          <MA_EMP_BT>
            <TEL_NO>9960125633</TEL_NO>
          </MA_EMP_BT>
        </MA_EMP>
      </MA>
      <JA>
        <FST_NME>JAYSHRI</FST_NME>
        <LST_NME>NAVANDAR</LST_NME>
        <DOB>1971-01-01</DOB>
        <AGE>52</AGE>
        <GNDR>FEMALE</GNDR>
        <JA_CA>
          <ADD>W O SANTOSH NAVANDAR SAMBHAJI NAGAR</ADD>
          <CTY>Jalna</CTY>
          <STE>Maharashtra</STE>
          <CTRY>India</CTRY>
          <PIN>431203</PIN>
        </JA_CA>
      </JA>
      <RF>
        <FST_NME>SANJAY</FST_NME>
        <LST_NME>NIKAM</LST_NME>
        <RF_MT>
          <TEL_NO>7385648626</TEL_NO>
        </RF_MT>
      </RF>
      <RF>
        <FST_NME>SANTOSH</FST_NME>
        <LST_NME>KURLIYE</LST_NME>
        <RF_MT>
          <TEL_NO>7385648626</TEL_NO>
        </RF_MT>
      </RF>
    </SUBMISSION>
    <SUBMISSION>
      <APP_VAL>507461</APP_VAL>
      <TERM>180</TERM>
      <CLASSIFICATION>UNKNOWN</CLASSIFICATION>
      <IDENTIFIER>N_APPL05299483_NHOU</IDENTIFIER>
      <PRODUCT>NHL_IND</PRODUCT>
      <DATE>2023-11-17</DATE>
      <APP_DTE>2023-11-17</APP_DTE>
      <BRNCH_RGN>BIJNOR</BRNCH_RGN>
      <MA>
        <PAN>ACZPF8287H</PAN>
        <FST_NME>FAIM</FST_NME>
        <LST_NME>FAIM</LST_NME>
        <DOB>1989-01-01</DOB>
        <AGE>34</AGE>
        <GNDR>MALE</GNDR>
        <MA_CA>
          <ADD>MOHALLA RAMPURA NEAR ABUBAKAR MASJID NAJIABBAD UTTAR PRADESH </ADD>
          <CTY>Bijnor</CTY>
          <STE>Uttar Pradesh</STE>
          <CTRY>India</CTRY>
          <PIN>246763</PIN>
        </MA_CA>
        <MA_PMA>
          <ADD>MOHALLA RAMPURA NEAR ABUBAKAR MASJID NAJIABBAD UTTAR PRADESH </ADD>
          <CTY>Bijnor</CTY>
          <STE>Uttar Pradesh</STE>
          <CTRY>India</CTRY>
          <PIN>246763</PIN>
        </MA_PMA>
        <MA_MT>
          <TEL_NO>9149247156</TEL_NO>
        </MA_MT>
        <MA_BNK>
          <BNK_NM>CANARA BANK</BNK_NM>
          <ACC_NO>93162010008000</ACC_NO>
        </MA_BNK>
      </MA>
      <JA>
        <PAN>EXYPR3727Q</PAN>
        <FST_NME>RUBEENA</FST_NME>
        <LST_NME>RUBEENA</LST_NME>
        <DOB>1992-01-01</DOB>
        <AGE>31</AGE>
        <GNDR>FEMALE</GNDR>
        <JA_CA>
          <ADD>MOHALLA RAMPURA NEAR ABUBAKAR MASJID NAJIABBAD UTTAR PRADESH </ADD>
          <CTY>Bijnor</CTY>
          <STE>Uttar Pradesh</STE>
          <CTRY>India</CTRY>
          <PIN>246763</PIN>
        </JA_CA>
      </JA>
      <RF>
        <FST_NME>SHANABAZ</FST_NME>
        <RF_MT>
          <TEL_NO>7534045564</TEL_NO>
        </RF_MT>
      </RF>
      <RF>
        <FST_NME>MOHD</FST_NME>
        <LST_NME>USMAN</LST_NME>
        <RF_MT>
          <TEL_NO>7534045564</TEL_NO>
        </RF_MT>
      </RF>
    </SUBMISSION>
    <SUBMISSION>
      <APP_VAL>1988232</APP_VAL>
      <TERM>120</TERM>
      <CLASSIFICATION>UNKNOWN</CLASSIFICATION>
      <IDENTIFIER>S_APPL05299271_NHOU</IDENTIFIER>
      <PRODUCT>NHL_IND</PRODUCT>
      <DATE>2023-11-17</DATE>
      <APP_DTE>2023-11-17</APP_DTE>
      <BRNCH_RGN>PRODDATUR</BRNCH_RGN>
      <MA>
        <PAN>CCUPR0621Q</PAN>
        <FST_NME>ALAMURU</FST_NME>
        <LST_NME>RABBANI</LST_NME>
        <DOB>1999-03-14</DOB>
        <AGE>24</AGE>
        <GNDR>MALE</GNDR>
        <MA_CA>
          <ADD>6-271,MAHARAJA COLONYKOTHAPALLEPRODDATUR </ADD>
          <CTY>Cuddapah</CTY>
          <STE>Andhra Pradesh</STE>
          <CTRY>India</CTRY>
          <PIN>516362</PIN>
        </MA_CA>
        <MA_PMA>
          <ADD>6-271,MAHARAJA COLONYKOTHAPALLEPRODDATUR </ADD>
          <CTY>Cuddapah</CTY>
          <STE>Andhra Pradesh</STE>
          <CTRY>India</CTRY>
          <PIN>516362</PIN>
        </MA_PMA>
        <MA_MT>
          <TEL_NO>7730007099</TEL_NO>
        </MA_MT>
        <MA_EMP>
          <ORG_NME>AMG VEGETBLE MERCHANTS </ORG_NME>
          <EMP_IND>OTHER</EMP_IND>
          <MA_EMP_AD>
            <ADD>ROOM NO 4,5,6,7NEW MARKETPRODDATUR </ADD>
            <CTY>Cuddapah</CTY>
            <STE>Andhra Pradesh</STE>
            <CTRY>India</CTRY>
            <PIN>516360</PIN>
          </MA_EMP_AD>
          <MA_EMP_BT>
            <TEL_NO>7730007099</TEL_NO>
          </MA_EMP_BT>
        </MA_EMP>
      </MA>
      <JA>
        <PAN>DGWPA1848D</PAN>
        <FST_NME>ALAMURU</FST_NME>
        <LST_NME>SHAGGO</LST_NME>
        <DOB>2001-06-10</DOB>
        <AGE>22</AGE>
        <GNDR>FEMALE</GNDR>
        <JA_CA>
          <ADD>6-271,MAHARAJA COLONYKOTHAPALLEPRODDATUR </ADD>
          <CTY>Cuddapah</CTY>
          <STE>Andhra Pradesh</STE>
          <CTRY>India</CTRY>
          <PIN>516362</PIN>
        </JA_CA>
      </JA>
      <RF>
        <FST_NME>SYED</FST_NME>
        <LST_NME>RAZAQ</LST_NME>
        <RF_MT>
          <TEL_NO>7893746042</TEL_NO>
        </RF_MT>
      </RF>
      <RF>
        <FST_NME>SHAIK</FST_NME>
        <LST_NME>BASHA</LST_NME>
        <RF_MT>
          <TEL_NO>7893746042</TEL_NO>
        </RF_MT>
      </RF>
    </SUBMISSION>
    <SUBMISSION>
      <APP_VAL>938147</APP_VAL>
      <TERM>120</TERM>
      <CLASSIFICATION>UNKNOWN</CLASSIFICATION>
      <IDENTIFIER>S_APPL05298633_NHOU</IDENTIFIER>
      <PRODUCT>NHL_IND</PRODUCT>
      <DATE>2023-11-17</DATE>
      <APP_DTE>2023-11-17</APP_DTE>
      <BRNCH_RGN>NANDYAL</BRNCH_RGN>
      <MA>
        <PAN>ISLPM4121H</PAN>
        <FST_NME>MOLLA</FST_NME>
        <MID_NME>ABDUL</MID_NME>
        <LST_NME>SAMAD</LST_NME>
        <DOB>1969-06-10</DOB>
        <AGE>54</AGE>
        <GNDR>MALE</GNDR>
        <MA_CA>
          <ADD>HNO 3-210-148 VELPANUR V VELGODU M NANDYAL D  Kurnool, Velpanur, Velpanur ANDHRA PRADESH, INDIA, 518533</ADD>
          <CTY>Kurnool</CTY>
          <STE>Andhra Pradesh</STE>
          <CTRY>India</CTRY>
          <PIN>518533</PIN>
        </MA_CA>
        <MA_PMA>
          <ADD>HNO 3-210-148 VELPANUR V VELGODU M NANDYAL D  KURNOOL, VELPANUR, VELPANUR ANDHRA PRADESH, INDIA, 518533</ADD>
          <CTY>Kurnool</CTY>
          <STE>Andhra Pradesh</STE>
          <CTRY>India</CTRY>
          <PIN>518533</PIN>
        </MA_PMA>
        <MA_MT>
          <TEL_NO>7093551873</TEL_NO>
        </MA_MT>
      </MA>
      <JA>
        <PAN>ECPPR7521J</PAN>
        <FST_NME>MOLLA</FST_NME>
        <MID_NME>RIYAZUL</MID_NME>
        <LST_NME>RAHIMAN</LST_NME>
        <DOB>1996-06-15</DOB>
        <AGE>27</AGE>
        <GNDR>MALE</GNDR>
        <JA_CA>
          <ADD>HNO 3-210-148 VELPANUR V VELGODU M NANDYAL D  KURNOOL, VELPANUR, VELPANUR ANDHRA PRADESH, INDIA, 518533</ADD>
          <CTY>Kurnool</CTY>
          <STE>Andhra Pradesh</STE>
          <CTRY>India</CTRY>
          <PIN>518533</PIN>
        </JA_CA>
      </JA>
      <JA>
        <FST_NME>MOLLA</FST_NME>
        <MID_NME>NOORJAHAN</MID_NME>
        <LST_NME>BEE</LST_NME>
        <DOB>1969-01-01</DOB>
        <AGE>54</AGE>
        <GNDR>FEMALE</GNDR>
        <JA_CA>
          <ADD>HNO 3-210-148 VELPANUR V VELGODU M NANDYAL D VELPANUR V</ADD>
          <CTY>Kurnool</CTY>
          <STE>Andhra Pradesh</STE>
          <CTRY>India</CTRY>
          <PIN>518533</PIN>
        </JA_CA>
      </JA>
      <RF>
        <FST_NME>ISMAIL</FST_NME>
        <RF_MT>
          <TEL_NO>7382873438</TEL_NO>
        </RF_MT>
      </RF>
      <RF>
        <FST_NME>JAKEER</FST_NME>
        <RF_MT>
          <TEL_NO>7382873438</TEL_NO>
        </RF_MT>
      </RF>
    </SUBMISSION>
    <SUBMISSION>
      <APP_VAL>657882</APP_VAL>
      <TERM>180</TERM>
      <CLASSIFICATION>UNKNOWN</CLASSIFICATION>
      <IDENTIFIER>N_APPL05299224_NHOU</IDENTIFIER>
      <PRODUCT>NHL_IND</PRODUCT>
      <DATE>2023-11-17</DATE>
      <APP_DTE>2023-11-17</APP_DTE>
      <BRNCH_RGN>HATHRAS</BRNCH_RGN>
      <MA>
        <PAN>AIMPV2745B</PAN>
        <FST_NME>PRABHAT</FST_NME>
        <LST_NME>VARSHNEY</LST_NME>
        <DOB>1990-08-15</DOB>
        <AGE>33</AGE>
        <GNDR>MALE</GNDR>
        <MA_CA>
          <ADD>S O SANTOSH KUMAR VARSHNEY,GANDE NALE KE SAMNE,PURANI SABJI MANDI</ADD>
          <CTY>Hathras</CTY>
          <STE>Uttar Pradesh</STE>
          <CTRY>India</CTRY>
          <PIN>204216</PIN>
        </MA_CA>
        <MA_PMA>
          <ADD>S O SANTOSH KUMAR VARSHNEY,GANDE NALE KE SAMNE,PURANI SABJI MANDI</ADD>
          <CTY>Hathras</CTY>
          <STE>Uttar Pradesh</STE>
          <CTRY>India</CTRY>
          <PIN>204216</PIN>
        </MA_PMA>
        <MA_MT>
          <TEL_NO>7830655125</TEL_NO>
        </MA_MT>
        <MA_BNK>
          <BNK_NM>PUNJAB NATIONAL BANK</BNK_NM>
          <ACC_NO>36383</ACC_NO>
        </MA_BNK>
        <MA_EMP>
          <ORG_NME>M/S 'Shree Ram Water Fitting &amp; Sanitary' </ORG_NME>
          <EMP_IND>OTHER</EMP_IND>
          <MA_EMP_AD>
            <ADD>PURANI SABJI MANDI SASNI HATHRAS</ADD>
            <CTY>Hathras</CTY>
            <STE>Uttar Pradesh</STE>
            <CTRY>India</CTRY>
            <PIN>204216</PIN>
          </MA_EMP_AD>
          <MA_EMP_BT>
            <TEL_NO>7830655125</TEL_NO>
          </MA_EMP_BT>
        </MA_EMP>
      </MA>
      <JA>
        <PAN>BKIPV6258C</PAN>
        <FST_NME>MADHU</FST_NME>
        <LST_NME>VARSHNEY</LST_NME>
        <DOB>1970-01-01</DOB>
        <AGE>53</AGE>
        <GNDR>FEMALE</GNDR>
        <JA_CA>
          <ADD>S O SANTOSH KUMAR VARSHNEY,GANDE NALE KE SAMNE,PURANI SABJI MANDI</ADD>
          <CTY>Hathras</CTY>
          <STE>Uttar Pradesh</STE>
          <CTRY>India</CTRY>
          <PIN>204216</PIN>
        </JA_CA>
      </JA>
      <JA>
        <PAN>AULPG5208K</PAN>
        <FST_NME>NEELAM</FST_NME>
        <LST_NME>GUPTA</LST_NME>
        <DOB>1990-09-01</DOB>
        <AGE>33</AGE>
        <GNDR>FEMALE</GNDR>
        <JA_CA>
          <ADD>S O SANTOSH KUMAR VARSHNEY,GANDE NALE KE SAMNE,PURANI SABJI MANDI</ADD>
          <CTY>Hathras</CTY>
          <STE>Uttar Pradesh</STE>
          <CTRY>India</CTRY>
          <PIN>204216</PIN>
        </JA_CA>
      </JA>
      <JA>
        <PAN>ARVPV8925D</PAN>
        <FST_NME>PRAVEEN</FST_NME>
        <MID_NME>KUMAR</MID_NME>
        <LST_NME>VARSHNEY</LST_NME>
        <DOB>1991-07-15</DOB>
        <AGE>32</AGE>
        <GNDR>MALE</GNDR>
        <JA_CA>
          <ADD>NALE KE SAMANE AGRA ROAD SASNI HATHRAS</ADD>
          <CTY>Hathras</CTY>
          <STE>Uttar Pradesh</STE>
          <CTRY>India</CTRY>
          <PIN>204216</PIN>
        </JA_CA>
      </JA>
      <BR>
        <ORG_CD>5718</ORG_CD>
        <ORG_NME>Sagar Sharma</ORG_NME>
      </BR>
      <RF>
        <FST_NME>SANTOSH</FST_NME>
        <LST_NME>DIXIT</LST_NME>
        <RF_MT>
          <TEL_NO>9675088329</TEL_NO>
        </RF_MT>
      </RF>
      <RF>
        <FST_NME>ROHIT</FST_NME>
        <RF_MT>
          <TEL_NO>9675088329</TEL_NO>
        </RF_MT>
      </RF>
    </SUBMISSION>
  </SUBMISSIONS>
</BATCH>
