<?xml version="1.0" encoding="UTF-8" standalone="no"?>
<BATCH xmlns="urn:mclsoftware.co.uk:hunterII" xmlns:xsd="http://www.w3.org/2001/XMLSchema" xmlns:xsi="http://www.w3.org/2001/XMLSchema-instance">
  <HEADER>
    <COUNT>1</COUNT>
    <ORIGINATOR>SHDFC</ORIGINATOR>
  </HEADER>
  <SUBMISSIONS>
    <SUBMISSION>
      <APP_VAL>915233</APP_VAL>
      <TERM>240</TERM>
      <CLASSIFICATION>UNKNOWN</CLASSIFICATION>
      <IDENTIFIER>N_APPL05222116_HOU</IDENTIFIER>
      <PRODUCT>HL_IND</PRODUCT>
      <DATE>2022-09-10</DATE>
      <APP_DTE>2022-09-09</APP_DTE>
      <BRNCH_RGN>Delhi-Dwarka More</BRNCH_RGN>
      <MA>
        <PAN>AHGPV9903J</PAN>
        <FST_NME>VIKRANT</FST_NME>
        <LST_NME>VISHWAKARMA</LST_NME>
        <DOB>1980-07-23</DOB>
        <AGE>42</AGE>
        <GNDR>MALE</GNDR>
        <MA_CA>
          <ADD>A 2 37 HASTSAL RD UTTAM NGR</ADD>
          <CTY>West Delhi</CTY>
          <STE>Delhi</STE>
          <CTRY>India</CTRY>
          <PIN>110059</PIN>
        </MA_CA>
        <MA_PMA>
          <ADD>HNO 98 DEEN DAYAL WARD 90 QUATER TRIMURTI NGR</ADD>
          <CTY>Jabalpur</CTY>
          <STE>Madhya Pradesh</STE>
          <CTRY>India</CTRY>
          <PIN>482001</PIN>
        </MA_PMA>
        <MA_PROP>
          <ADD>NANGLOI</ADD>
          <CTY>West Delhi</CTY>
          <STE>Delhi</STE>
          <CTRY>India</CTRY>
          <PIN>110041</PIN>
        </MA_PROP>
        <MA_MT>
          <TEL_NO>8010275836</TEL_NO>
        </MA_MT>
        <MA_BNK>
          <BNK_NM>HDFC BANK</BNK_NM>
          <ACC_NO>273001201301</ACC_NO>
        </MA_BNK>
        <MA_EMP>
          <ORG_NME>SANAT PRODUCT</ORG_NME>
          <EMP_IND>OTHER</EMP_IND>
          <MA_EMP_AD>
            <ADD>A 36 SEC 60 NOIDA</ADD>
            <CTY>Bulandsahar</CTY>
            <STE>Uttar Pradesh</STE>
            <CTRY>India</CTRY>
            <PIN>203205</PIN>
          </MA_EMP_AD>
        </MA_EMP>
      </MA>
      <JA>
        <PAN>AVFPD1937M</PAN>
        <FST_NME>POOJA</FST_NME>
        <LST_NME>DWIVEDI</LST_NME>
        <DOB>1989-05-01</DOB>
        <AGE>33</AGE>
        <GNDR>FEMALE</GNDR>
        <JA_CA>
          <ADD>A 2 37 HASTSAL RD UTTAM NGR</ADD>
          <CTY>West Delhi</CTY>
          <STE>Delhi</STE>
          <CTRY>India</CTRY>
          <PIN>110059</PIN>
        </JA_CA>
      </JA>
      <RF>
        <FST_NME>ARCHANA</FST_NME>
        <RF_CA>
          <ADD>VIKAS PURI</ADD>
          <CTY>West Delhi</CTY>
          <STE>Delhi</STE>
          <CTRY>India</CTRY>
          <PIN>110059</PIN>
        </RF_CA>
        <RF_MT>
          <TEL_NO>8851476053</TEL_NO>
        </RF_MT>
      </RF>
      <RF>
        <FST_NME>ANOOP</FST_NME>
        <RF_CA>
          <ADD>VIKAS PURI</ADD>
          <CTY>West Delhi</CTY>
          <STE>Delhi</STE>
          <CTRY>India</CTRY>
          <PIN>110059</PIN>
        </RF_CA>
        <RF_MT>
          <TEL_NO>8851476053</TEL_NO>
        </RF_MT>
      </RF>
    </SUBMISSION>
  </SUBMISSIONS>
</BATCH>
